Workbook
Name active: Assumptions!$I$25:$I$30
Name AddressOfCells: _xlfn.LAMBDA(_xlpm.Array,_xlfn.MAP(_xlpm.Array,_xlfn.LAMBDA(_xlpm.a,ADDRESS(ROW(_xlpm.a),COLUMN(_xlpm.a),4))))
Name Alphabet: _xlfn.LAMBDA(CHAR(_xlfn.SEQUENCE(26,,65)))
Name AlphaShift: _xlfn.LAMBDA(_xlpm.startcode,_xlpm.adjustment,_xlpm.startingletter,MOD(_xlpm.startcode+_xlpm.adjustment-_xlpm.startingletter,26)+_xlpm.startingletter)
Name Arrows: _xlfn.LAMBDA(_xlop.ShowHV,IF(_xlpm.ShowHV,{"↓",1,0;"↑",-1,0;"→",0,1;"←",0,-1;"↘",1,1;"↖",-1,-1;"↙",1,-1;"↗",-1,1},{"↓";"↑";"→";"←";"↘";"↖";"↙";"↗"}))
Name BoardGameMove: _xlfn.LAMBDA(_xlpm.MoveValue,_xlpm.EndSpace,MOD(_xlpm.MoveValue-1,_xlpm.EndSpace)+1)
Name cust: Assumptions!$B$25:$B$30
Name DiceNumExtract: _xlfn.LAMBDA(_xlpm.Dice,_xlfn.UNICODE(_xlpm.Dice)-9855)
Name Exists: _xlfn.LAMBDA(_xlpm.Item,_xlpm.List,_xlop.SearchMode,ISNUMBER(IF(_xlpm.SearchMode,_xleta.SEARCH,_xleta.XMATCH)(_xlpm.Item,_xlpm.List)))
Name ib_rate: Assumptions!$H$25:$H$30
Name inpal: Assumptions!$G$25:$G$30
Name month: Assumptions!$D$25:$D$30
Name pal: Assumptions!$H$25:$H$30
Name PPP: Assumptions!$F$25:$F$30
Name RowNum: _xlfn.LAMBDA(_xlpm.addresses,IF(ISNUMBER(_xlpm.addresses),INT(_xlpm.addresses/10^6),1*_xlfn.TEXTAFTER(UPPER(_xlpm.addresses),Alphabet(),-1)))
Name seg: Assumptions!$C$25:$C$30
Name starting_parc: Assumptions!$E$25:$E$30
Name Tlookup: _xlfn.LAMBDA(_xlpm.Table,_xlpm.Rowitem,_xlpm.Columnitem,INDEX(_xlpm.Table,_xlfn.XMATCH(_xlpm.Rowitem,_xlfn.TAKE(_xlpm.Table,,1)),_xlfn.XMATCH(_xlpm.Columnitem,_xlfn.TAKE(_xlpm.Table,1))))

Sheet Cover
C1: X-Logistic Services (XLS)
C2: 5-Year Monthly Financial Projection Model
C3: EBITDA Forecast | New Client Evaluation | 61-Month Projection Horizon
C6: Model Purpose: | D6: 5-year monthly EBITDA projection for strategic client decision-making
C7: New Client Toggle: | D7: Single-switch scenario — evaluate results with / without Tim Forward Brands
C8: Projection Period: | D8: January 2026 — December 2030 (61 months)
C9: Industries: | D9: Third-Party Logistics (3PL) | Retail | E-commerce | Industrial
C10: Service Lines: | D10: Inbound Handling · Outbound Picking · Outbound Handling · Storage
C11: Built By: | D11: Alicia Bruce
C12: Competition: | D12: Financial Modeling World Cup (FMWC)
A14: Built using a Financial Modeling World Cup case. Synthetic data — for portfolio demonstration purposes only.

Sheet Dashboard Summary
C1: X-Logistic Services (XLS) Dashboard
C4: With Tom Forward Brands* | D4: Off
C6: Total Revenue | D6: =SUM(Model!D20) -> 1.2415581e+08
C7: EBITDA | D7: =Model!D26 -> 55621678
C8: EBITDA Margin | D8: =D7/D6 -> 0.44799899
C9: Total Labor Costs | D9: =SUM(Model!H245:BO245) -> 59230113
C10: Temp Labor % | D10: =SUM(Model!H244:BO244)/'Dashboard Summary'!D9 -> 0.18824987
C11: Total Capex | D11: =SUM(Model!H326:BO326) -> 1254790.3
C15: Client Impact Summary
D16: Without Client | E16: With Client | F16: Gain/Loss
C17: Revenue | D17: =Assumptions!N25 -> 1.2415581e+08 | E17: =Assumptions!N24 -> 1.3652408e+08 | F17: =E17-D17 -> 12368269
C18: EBITDA | D18: =Assumptions!N29 -> 55621678 | E18: =Assumptions!N28 -> 61161159 | F18: =E18-D18 -> 5539480.9
C19: CAPEX | D19: =Assumptions!N33 -> 1254790.3 | E19: =Assumptions!N32 -> 2036472.6 | F19: =E19-D19 -> 781682.26
A21: *Toggle also powers model to turn on and off the addtion of Tom Forward Brands

Sheet Assumptions
K1: Calculations Added for Model
B2: X-Logistic Services (XLS)
B3: Inputs and Assumptions | M3: On
M4: Off
B5: 1. General Assumptions
B7: General Assumptions | F7: Staff Information
B8: Company Name | C8: [Date] | D8: X-Logistic Service | F8: Permanent staff | G8: [FTE] | H8: 174
B9: First Year of Projections | C9: [Date] | D9: 2026 | F9: Monthly FTE Hours | G9: [Hours/FTE] | H9: 160
B10: Annual Inflation | C10: [% p.a.] | D10: 0.03 | F10: Working shifts | G10: [#] | H10: 3
B11: SG&A | C11: [$/month] | D11: 62500 | F11: Permanent staff Cost | G11: [$/FTE/Month] | H11: 4160
B12: Energy Price | C12: [$/kWh] | D12: 0.18 | F12: Temporary staff Cost | G12: [$/FTE/Month] | H12: 5120
B13: Fixed COGS | C13: [$/month] | D13: 60000
F14: Staff Productivity per Activity | H14: Staff Productivity
B15: Service Prices | F15: Inbound unloading | G15: [Inbound Pallets/Hour] | H15: 12
B16: Inbound handling | C16: [$/Inbound Pallet] | D16: 4.5 | F16: Putaway to rack | G16: [Inbound Pallets/Hour] | H16: 10
B17: Outbound picking | C17: [$/Outbound Parcel] | D17: 0.35 | F17: Picking | G17: [Outbound Parcels/Hour] | H17: 180
B18: Outbound handling | C18: [$/Outbound Pallet] | D18: 5 | F18: Replenishment | G18: [Outbound Pallets/Hour] | H18: 15
B19: Storage rack | C19: [$/Pallet/Month] | D19: 6 | F19: Outbound loading | G19: [Outbound Pallets/Hour] | H19: 14
B22: 2. Client Data
L23: Revenue — With and Without Tim Forward Brands | N23: =Model!D20 -> 1.2415581e+08
B24: Client Name | C24: Segment | D24: Starting Month | E24: Monthly Outbound Parcels | F24: Parcels Per Pallet | G24: Initial Balance (Pallets) | H24: Assortment Growth Rate | I24: Contract Active | L24: With | M24: 1 | N24: 1.3652408e+08
B25: Michael’s Market Goods | C25: Retail | D25: 1 | E25: 375000 | F25: 18 | G25: 2400 | H25: 0.03 | I25: 1 | L25: Without | M25: 0 | N25: 1.2415581e+08
B26: Andrew Digital Commerce | C26: E-commerce | D26: 1 | E26: 450000 | F26: 30 | G26: 2100 | H26: 0.06 | I26: 1
B27: Anup Industrial Systems | C27: Industrial | D27: 1 | E27: 225000 | F27: 15 | G27: 1800 | H27: 0.01 | I27: 1 | L27: EBITDA — With and Without Tim Forward Brands | N27: =Model!D26 -> 55621678
B28: Joseph Retail Group | C28: Retail | D28: 1 | E28: 300000 | F28: 22 | G28: 2700 | H28: 0 | I28: 1 | L28: With | M28: 1 | N28: 61161159
B29: Dim Collective | C29: Retail | D29: 1 | E29: 125000 | F29: 25 | G29: 900 | H29: 0.08 | I29: 1 | L29: Without | M29: 0 | N29: 55621678
B30: Tim Forward Brands | C30: Retail | D30: 37 | E30: 250000 | F30: 15 | G30: 1500 | H30: 0.09 | I30: =IF('Dashboard Summary'!D4="Off",0,1) -> 0
L31: CapEx — With and Without Tim Forward Brands | N31: =SUM(Model!H326:BO326) -> 1254790.3
L32: With | M32: 1 | N32: 2036472.6
B33: 3. Customers Volume Growth | L33: Without | M33: 0 | N33: 1254790.3
B35: Client Name | D35: 1 | E35: 2 | F35: 3 | G35: 4 | H35: 5 | I35: 0 | K35: 1 | L35: 2 | M35: 3 | N35: 4 | O35: 5 | P35: 6
B36: Michael’s Market Goods | D36: 0.07 | E36: 0.05 | F36: 0.05 | G36: 0.03 | H36: 0.02 | I36: {=starting_parc} -> 375000 | K36: {=_xlfn.ANCHORARRAY(I36)*(1+D36:D41)} -> 401250 | L36: {=_xlfn.ANCHORARRAY(K36)*(1+E36:E41)} -> 421312.5 | M36: {=_xlfn.ANCHORARRAY(L36)*(1+F36:F41)} -> 442378.12 | N36: {=_xlfn.ANCHORARRAY(M36)*(1+G36:G41)} -> 455649.47 | O36: {=_xlfn.ANCHORARRAY(N36)*(1+H36:H41)} -> 464762.46 | P36: {=_xlfn.ANCHORARRAY(O36)*(1+H36:H41)} -> 474057.71
B37: Andrew Digital Commerce | D37: 0.12 | E37: 0.06 | F37: 0.02 | G37: 0 | H37: 0 | I37: 450000 | K37: 504000 | L37: 534240 | M37: 544924.8 | N37: 544924.8 | O37: 544924.8 | P37: 544924.8
B38: Anup Industrial Systems | D38: 0.01 | E38: 0.005 | F38: 0 | G38: -0.01 | H38: -0.015 | I38: 225000 | K38: 227250 | L38: 228386.25 | M38: 228386.25 | N38: 226102.39 | O38: 222710.85 | P38: 219370.19
B39: Joseph Retail Group | D39: -0.08 | E39: -0.04 | F39: -0.06 | G39: -0.08 | H39: -0.07 | I39: 300000 | K39: 276000 | L39: 264960 | M39: 249062.4 | N39: 229137.41 | O39: 213097.79 | P39: 198180.94
B40: Dim Collective | D40: 0.3 | E40: 0.15 | F40: 0.1 | G40: 0.06 | H40: 0.04 | I40: 125000 | K40: 162500 | L40: 186875 | M40: 205562.5 | N40: 217896.25 | O40: 226612.1 | P40: 235676.58
B41: Tim Forward Brands | D41: 0 | E41: 0 | F41: 0 | G41: 0.1448 | H41: 0.04 | I41: 250000 | K41: 250000 | L41: 250000 | M41: 250000 | N41: 286200 | O41: 297648 | P41: 309553.92
H42: CustomerVolumeGrowthIn
B44: 4. Seasonality per Client Segment
B46: Month | D46: Retail | E46: E-commerce | F46: Industrial | G46: SegmentsNameIn
B47: 1 | D47: 0.75 | E47: 0.75 | F47: 0.95
B48: 2 | D48: 0.8 | E48: 0.65 | F48: 0.95
B49: 3 | D49: 0.85 | E49: 0.7 | F49: 1
B50: 4 | D50: 0.95 | E50: 0.75 | F50: 1
B51: 5 | D51: 1.1 | E51: 0.7 | F51: 1
B52: 6 | D52: 1.2 | E52: 0.75 | F52: 1
B53: 7 | D53: 0.9 | E53: 0.7 | F53: 0.95
B54: 8 | D54: 0.85 | E54: 0.9 | F54: 0.9
B55: 9 | D55: 1 | E55: 1.05 | F55: 1.1
B56: 10 | D56: 1.05 | E56: 1.1 | F56: 1.1
B57: 11 | D57: 1.2 | E57: 1.75 | F57: 1.05
B58: 12 | D58: 1.35 | E58: 2.2 | F58: 1
F59: SegmentsSeasonalityIn
B61: 5. Equipment Data
B63: Current Equipment Owned | F63: Activity | G63: Equipment Used | I63: Utilization
B64: Powered Pallet Truck | C64: [Units] | D64: 35 | F64: Inbound unloading | G64: Powered Pallet Truck | H64: [h/Inbound Pallet] | I64: 0.07
B65: Reach Truck | C65: [Units] | D65: 25 | F65: Putaway to rack | G65: Reach Truck | H65: [h/Inbound Pallet] | I65: 0.085
F66: Picking | G66: Powered Pallet Truck | H66: [h/Outbound Parcel] | I66: 0.0055
B67: Equipment Purchase Price | F67: Replenishment | G67: Reach Truck | H67: [h/Outbound Pallet] | I67: 0.065
B68: Powered Pallet Truck | C68: [$/Unit] | D68: 22000 | F68: Outbound loading | G68: Powered Pallet Truck | H68: [h/Outbound Pallet] | I68: 0.065
B69: Reach Truck | C69: [$/Unit] | D69: 45000 | G69: ActivityEquipmentIn
B71: Current Power Consumption
B72: Powered Pallet Truck | C72: [kWh] | D72: 2.5
B73: Reach Truck | C73: [kWh] | D73: 7

Sheet Financial Model
B2: =Assumptions!D8 -> X-Logistic Service
C4: Period # | D4: 0 | E4: {=Timeline(Assumptions!D9,5)} -> 1 | F4: 2 | G4: 3 | H4: 4 | I4: 5 | J4: 6 | K4: 7 | L4: 8 | M4: 9 | N4: 10 | O4: 11 | P4: 12 | Q4: 13 | R4: 14 | S4: 15 | T4: 16 | U4: 17 | V4: 18 | W4: 19 | X4: 20 | Y4: 21 | Z4: 22 | AA4: 23 | AB4: 24 | AC4: 25 | AD4: 26 | AE4: 27 | AF4: 28 | AG4: 29 | AH4: 30 | AI4: 31 | AJ4: 32 | AK4: 33 | AL4: 34 | AM4: 35 | AN4: 36 | AO4: 37 | AP4: 38 | AQ4: 39 | AR4: 40 | AS4: 41 | AT4: 42 | AU4: 43 | AV4: 44 | AW4: 45 | AX4: 46 | AY4: 47 | AZ4: 48 | BA4: 49 | BB4: 50 | BC4: 51 | BD4: 52 | BE4: 53 | BF4: 54 | BG4: 55 | BH4: 56 | BI4: 57 | BJ4: 58 | BK4: 59 | BL4: 60 | BM4: =BL4+1 -> 61
C5: Start Date | D5: 45992 | E5: 46023 | F5: 46054 | G5: 46082 | H5: 46113 | I5: 46143 | J5: 46174 | K5: 46204 | L5: 46235 | M5: 46266 | N5: 46296 | O5: 46327 | P5: 46357 | Q5: 46388 | R5: 46419 | S5: 46447 | T5: 46478 | U5: 46508 | V5: 46539 | W5: 46569 | X5: 46600 | Y5: 46631 | Z5: 46661 | AA5: 46692 | AB5: 46722 | AC5: 46753 | AD5: 46784 | AE5: 46813 | AF5: 46844 | AG5: 46874 | AH5: 46905 | AI5: 46935 | AJ5: 46966 | AK5: 46997 | AL5: 47027 | AM5: 47058 | AN5: 47088 | AO5: 47119 | AP5: 47150 | AQ5: 47178 | AR5: 47209 | AS5: 47239 | AT5: 47270 | AU5: 47300 | AV5: 47331 | AW5: 47362 | AX5: 47392 | AY5: 47423 | AZ5: 47453 | BA5: 47484 | BB5: 47515 | BC5: 47543 | BD5: 47574 | BE5: 47604 | BF5: 47635 | BG5: 47665 | BH5: 47696 | BI5: 47727 | BJ5: 47757 | BK5: 47788 | BL5: 47818 | BM5: =BL5+31 -> 47849
C6: End Date | D6: =EOMONTH(D5,0) -> 46022 | E6: 46053 | F6: 46081 | G6: 46112 | H6: 46142 | I6: 46173 | J6: 46203 | K6: 46234 | L6: 46265 | M6: 46295 | N6: 46326 | O6: 46356 | P6: 46387 | Q6: 46418 | R6: 46446 | S6: 46477 | T6: 46507 | U6: 46538 | V6: 46568 | W6: 46599 | X6: 46630 | Y6: 46660 | Z6: 46691 | AA6: 46721 | AB6: 46752 | AC6: 46783 | AD6: 46812 | AE6: 46843 | AF6: 46873 | AG6: 46904 | AH6: 46934 | AI6: 46965 | AJ6: 46996 | AK6: 47026 | AL6: 47057 | AM6: 47087 | AN6: 47118 | AO6: 47149 | AP6: 47177 | AQ6: 47208 | AR6: 47238 | AS6: 47269 | AT6: 47299 | AU6: 47330 | AV6: 47361 | AW6: 47391 | AX6: 47422 | AY6: 47452 | AZ6: 47483 | BA6: 47514 | BB6: 47542 | BC6: 47573 | BD6: 47603 | BE6: 47634 | BF6: 47664 | BG6: 47695 | BH6: 47726 | BI6: 47756 | BJ6: 47787 | BK6: 47817 | BL6: 47848 | BM6: =EOMONTH(BM5,0) -> 47879
C7: Year | D7: =YEAR(D5) -> 2025 | E7: 2026 | F7: 2026 | G7: 2026 | H7: 2026 | I7: 2026 | J7: 2026 | K7: 2026 | L7: 2026 | M7: 2026 | N7: 2026 | O7: 2026 | P7: 2026 | Q7: 2027 | R7: 2027 | S7: 2027 | T7: 2027 | U7: 2027 | V7: 2027 | W7: 2027 | X7: 2027 | Y7: 2027 | Z7: 2027 | AA7: 2027 | AB7: 2027 | AC7: 2028 | AD7: 2028 | AE7: 2028 | AF7: 2028 | AG7: 2028 | AH7: 2028 | AI7: 2028 | AJ7: 2028 | AK7: 2028 | AL7: 2028 | AM7: 2028 | AN7: 2028 | AO7: 2029 | AP7: 2029 | AQ7: 2029 | AR7: 2029 | AS7: 2029 | AT7: 2029 | AU7: 2029 | AV7: 2029 | AW7: 2029 | AX7: 2029 | AY7: 2029 | AZ7: 2029 | BA7: 2030 | BB7: 2030 | BC7: 2030 | BD7: 2030 | BE7: 2030 | BF7: 2030 | BG7: 2030 | BH7: 2030 | BI7: 2030 | BJ7: 2030 | BK7: 2030 | BL7: 2030 | BM7: =YEAR(BM5) -> 2031
C8: Month # | D8: =MONTH(D5) -> 12 | E8: 1 | F8: 2 | G8: 3 | H8: 4 | I8: 5 | J8: 6 | K8: 7 | L8: 8 | M8: 9 | N8: 10 | O8: 11 | P8: 12 | Q8: 1 | R8: 2 | S8: 3 | T8: 4 | U8: 5 | V8: 6 | W8: 7 | X8: 8 | Y8: 9 | Z8: 10 | AA8: 11 | AB8: 12 | AC8: 1 | AD8: 2 | AE8: 3 | AF8: 4 | AG8: 5 | AH8: 6 | AI8: 7 | AJ8: 8 | AK8: 9 | AL8: 10 | AM8: 11 | AN8: 12 | AO8: 1 | AP8: 2 | AQ8: 3 | AR8: 4 | AS8: 5 | AT8: 6 | AU8: 7 | AV8: 8 | AW8: 9 | AX8: 10 | AY8: 11 | AZ8: 12 | BA8: 1 | BB8: 2 | BC8: 3 | BD8: 4 | BE8: 5 | BF8: 6 | BG8: 7 | BH8: 8 | BI8: 9 | BJ8: 10 | BK8: 11 | BL8: 12 | BM8: =MONTH(BM5) -> 1
C9: Quarter # | D9: 4 | E9: 1 | F9: 1 | G9: 1 | H9: 2 | I9: 2 | J9: 2 | K9: 3 | L9: 3 | M9: 3 | N9: 4 | O9: 4 | P9: 4 | Q9: 1 | R9: 1 | S9: 1 | T9: 2 | U9: 2 | V9: 2 | W9: 3 | X9: 3 | Y9: 3 | Z9: 4 | AA9: 4 | AB9: 4 | AC9: 1 | AD9: 1 | AE9: 1 | AF9: 2 | AG9: 2 | AH9: 2 | AI9: 3 | AJ9: 3 | AK9: 3 | AL9: 4 | AM9: 4 | AN9: 4 | AO9: 1 | AP9: 1 | AQ9: 1 | AR9: 2 | AS9: 2 | AT9: 2 | AU9: 3 | AV9: 3 | AW9: 3 | AX9: 4 | AY9: 4 | AZ9: 4 | BA9: 1 | BB9: 1 | BC9: 1 | BD9: 2 | BE9: 2 | BF9: 2 | BG9: 3 | BH9: 3 | BI9: 3 | BJ9: 4 | BK9: 4 | BL9: 4 | BM9: 4
C10: Quarter Name | D10: =YEAR(D5) & "-Q" & D9 -> 2025-Q4 | E10: 2026-Q1 | F10: 2026-Q1 | G10: 2026-Q1 | H10: 2026-Q2 | I10: 2026-Q2 | J10: 2026-Q2 | K10: 2026-Q3 | L10: 2026-Q3 | M10: 2026-Q3 | N10: 2026-Q4 | O10: 2026-Q4 | P10: 2026-Q4 | Q10: 2027-Q1 | R10: 2027-Q1 | S10: 2027-Q1 | T10: 2027-Q2 | U10: 2027-Q2 | V10: 2027-Q2 | W10: 2027-Q3 | X10: 2027-Q3 | Y10: 2027-Q3 | Z10: 2027-Q4 | AA10: 2027-Q4 | AB10: 2027-Q4 | AC10: 2028-Q1 | AD10: 2028-Q1 | AE10: 2028-Q1 | AF10: 2028-Q2 | AG10: 2028-Q2 | AH10: 2028-Q2 | AI10: 2028-Q3 | AJ10: 2028-Q3 | AK10: 2028-Q3 | AL10: 2028-Q4 | AM10: 2028-Q4 | AN10: 2028-Q4 | AO10: 2029-Q1 | AP10: 2029-Q1 | AQ10: 2029-Q1 | AR10: 2029-Q2 | AS10: 2029-Q2 | AT10: 2029-Q2 | AU10: 2029-Q3 | AV10: 2029-Q3 | AW10: 2029-Q3 | AX10: 2029-Q4 | AY10: 2029-Q4 | AZ10: 2029-Q4 | BA10: 2030-Q1 | BB10: 2030-Q1 | BC10: 2030-Q1 | BD10: 2030-Q2 | BE10: 2030-Q2 | BF10: 2030-Q2 | BG10: 2030-Q3 | BH10: 2030-Q3 | BI10: 2030-Q3 | BJ10: 2030-Q4 | BK10: 2030-Q4 | BL10: 2030-Q4 | BM10: =YEAR(BM5) & "-Q" & BM9 -> 2031-Q4
C11: Operating Year | D11: {=D7:BM7-D7} -> 0 | E11: 1 | F11: 1 | G11: 1 | H11: 1 | I11: 1 | J11: 1 | K11: 1 | L11: 1 | M11: 1 | N11: 1 | O11: 1 | P11: 1 | Q11: 2 | R11: 2 | S11: 2 | T11: 2 | U11: 2 | V11: 2 | W11: 2 | X11: 2 | Y11: 2 | Z11: 2 | AA11: 2 | AB11: 2 | AC11: 3 | AD11: 3 | AE11: 3 | AF11: 3 | AG11: 3 | AH11: 3 | AI11: 3 | AJ11: 3 | AK11: 3 | AL11: 3 | AM11: 3 | AN11: 3 | AO11: 4 | AP11: 4 | AQ11: 4 | AR11: 4 | AS11: 4 | AT11: 4 | AU11: 4 | AV11: 4 | AW11: 4 | AX11: 4 | AY11: 4 | AZ11: 4 | BA11: 5 | BB11: 5 | BC11: 5 | BD11: 5 | BE11: 5 | BF11: 5 | BG11: 5 | BH11: 5 | BI11: 5 | BJ11: 5 | BK11: 5 | BL11: 5 | BM11: 6
B14: 1. P&L Statement
C16: CPI | D16: {=(1+Assumptions!D10)^(D7:BM7-'Financial Model'!E7)} -> 0.97087379 | E16: 1 | F16: 1 | G16: 1 | H16: 1 | I16: 1 | J16: 1 | K16: 1 | L16: 1 | M16: 1 | N16: 1 | O16: 1 | P16: 1 | Q16: 1.03 | R16: 1.03 | S16: 1.03 | T16: 1.03 | U16: 1.03 | V16: 1.03 | W16: 1.03 | X16: 1.03 | Y16: 1.03 | Z16: 1.03 | AA16: 1.03 | AB16: 1.03 | AC16: 1.0609 | AD16: 1.0609 | AE16: 1.0609 | AF16: 1.0609 | AG16: 1.0609 | AH16: 1.0609 | AI16: 1.0609 | AJ16: 1.0609 | AK16: 1.0609 | AL16: 1.0609 | AM16: 1.0609 | AN16: 1.0609 | AO16: 1.092727 | AP16: 1.092727 | AQ16: 1.092727 | AR16: 1.092727 | AS16: 1.092727 | AT16: 1.092727 | AU16: 1.092727 | AV16: 1.092727 | AW16: 1.092727 | AX16: 1.092727 | AY16: 1.092727 | AZ16: 1.092727 | BA16: 1.1255088 | BB16: 1.1255088 | BC16: 1.1255088 | BD16: 1.1255088 | BE16: 1.1255088 | BF16: 1.1255088 | BG16: 1.1255088 | BH16: 1.1255088 | BI16: 1.1255088 | BJ16: 1.1255088 | BK16: 1.1255088 | BL16: 1.1255088 | BM16: 1.1592741
B18: Seasonality
C19: {=seg} -> Retail | E19: {=VLOOKUP($E$8:$BM$8,Assumptions!$B$47:$F$58,_xlfn.XMATCH('Financial Model'!$C19,Assumptions!$B$46:$F$46))} -> 0.75 | F19: 0.8 | G19: 0.85 | H19: 0.95 | I19: 1.1 | J19: 1.2 | K19: 0.9 | L19: 0.85 | M19: 1 | N19: 1.05 | O19: 1.2 | P19: 1.35 | Q19: 0.75 | R19: 0.8 | S19: 0.85 | T19: 0.95 | U19: 1.1 | V19: 1.2 | W19: 0.9 | X19: 0.85 | Y19: 1 | Z19: 1.05 | AA19: 1.2 | AB19: 1.35 | AC19: 0.75 | AD19: 0.8 | AE19: 0.85 | AF19: 0.95 | AG19: 1.1 | AH19: 1.2 | AI19: 0.9 | AJ19: 0.85 | AK19: 1 | AL19: 1.05 | AM19: 1.2 | AN19: 1.35 | AO19: 0.75 | AP19: 0.8 | AQ19: 0.85 | AR19: 0.95 | AS19: 1.1 | AT19: 1.2 | AU19: 0.9 | AV19: 0.85 | AW19: 1 | AX19: 1.05 | AY19: 1.2 | AZ19: 1.35 | BA19: 0.75 | BB19: 0.8 | BC19: 0.85 | BD19: 0.95 | BE19: 1.1 | BF19: 1.2 | BG19: 0.9 | BH19: 0.85 | BI19: 1 | BJ19: 1.05 | BK19: 1.2 | BL19: 1.35 | BM19: 0.75
C20: E-commerce | E20: {=VLOOKUP($E$8:$BM$8,Assumptions!$B$47:$F$58,_xlfn.XMATCH('Financial Model'!$C20,Assumptions!$B$46:$F$46))} -> 0.75 | F20: 0.65 | G20: 0.7 | H20: 0.75 | I20: 0.7 | J20: 0.75 | K20: 0.7 | L20: 0.9 | M20: 1.05 | N20: 1.1 | O20: 1.75 | P20: 2.2 | Q20: 0.75 | R20: 0.65 | S20: 0.7 | T20: 0.75 | U20: 0.7 | V20: 0.75 | W20: 0.7 | X20: 0.9 | Y20: 1.05 | Z20: 1.1 | AA20: 1.75 | AB20: 2.2 | AC20: 0.75 | AD20: 0.65 | AE20: 0.7 | AF20: 0.75 | AG20: 0.7 | AH20: 0.75 | AI20: 0.7 | AJ20: 0.9 | AK20: 1.05 | AL20: 1.1 | AM20: 1.75 | AN20: 2.2 | AO20: 0.75 | AP20: 0.65 | AQ20: 0.7 | AR20: 0.75 | AS20: 0.7 | AT20: 0.75 | AU20: 0.7 | AV20: 0.9 | AW20: 1.05 | AX20: 1.1 | AY20: 1.75 | AZ20: 2.2 | BA20: 0.75 | BB20: 0.65 | BC20: 0.7 | BD20: 0.75 | BE20: 0.7 | BF20: 0.75 | BG20: 0.7 | BH20: 0.9 | BI20: 1.05 | BJ20: 1.1 | BK20: 1.75 | BL20: 2.2 | BM20: 0.75
C21: Industrial | E21: {=VLOOKUP($E$8:$BM$8,Assumptions!$B$47:$F$58,_xlfn.XMATCH('Financial Model'!$C21,Assumptions!$B$46:$F$46))} -> 0.95 | F21: 0.95 | G21: 1 | H21: 1 | I21: 1 | J21: 1 | K21: 0.95 | L21: 0.9 | M21: 1.1 | N21: 1.1 | O21: 1.05 | P21: 1 | Q21: 0.95 | R21: 0.95 | S21: 1 | T21: 1 | U21: 1 | V21: 1 | W21: 0.95 | X21: 0.9 | Y21: 1.1 | Z21: 1.1 | AA21: 1.05 | AB21: 1 | AC21: 0.95 | AD21: 0.95 | AE21: 1 | AF21: 1 | AG21: 1 | AH21: 1 | AI21: 0.95 | AJ21: 0.9 | AK21: 1.1 | AL21: 1.1 | AM21: 1.05 | AN21: 1 | AO21: 0.95 | AP21: 0.95 | AQ21: 1 | AR21: 1 | AS21: 1 | AT21: 1 | AU21: 0.95 | AV21: 0.9 | AW21: 1.1 | AX21: 1.1 | AY21: 1.05 | AZ21: 1 | BA21: 0.95 | BB21: 0.95 | BC21: 1 | BD21: 1 | BE21: 1 | BF21: 1 | BG21: 0.95 | BH21: 0.9 | BI21: 1.1 | BJ21: 1.1 | BK21: 1.05 | BL21: 1 | BM21: 0.95
C22: Retail | E22: {=VLOOKUP($E$8:$BM$8,Assumptions!$B$47:$F$58,_xlfn.XMATCH('Financial Model'!$C22,Assumptions!$B$46:$F$46))} -> 0.75 | F22: 0.8 | G22: 0.85 | H22: 0.95 | I22: 1.1 | J22: 1.2 | K22: 0.9 | L22: 0.85 | M22: 1 | N22: 1.05 | O22: 1.2 | P22: 1.35 | Q22: 0.75 | R22: 0.8 | S22: 0.85 | T22: 0.95 | U22: 1.1 | V22: 1.2 | W22: 0.9 | X22: 0.85 | Y22: 1 | Z22: 1.05 | AA22: 1.2 | AB22: 1.35 | AC22: 0.75 | AD22: 0.8 | AE22: 0.85 | AF22: 0.95 | AG22: 1.1 | AH22: 1.2 | AI22: 0.9 | AJ22: 0.85 | AK22: 1 | AL22: 1.05 | AM22: 1.2 | AN22: 1.35 | AO22: 0.75 | AP22: 0.8 | AQ22: 0.85 | AR22: 0.95 | AS22: 1.1 | AT22: 1.2 | AU22: 0.9 | AV22: 0.85 | AW22: 1 | AX22: 1.05 | AY22: 1.2 | AZ22: 1.35 | BA22: 0.75 | BB22: 0.8 | BC22: 0.85 | BD22: 0.95 | BE22: 1.1 | BF22: 1.2 | BG22: 0.9 | BH22: 0.85 | BI22: 1 | BJ22: 1.05 | BK22: 1.2 | BL22: 1.35 | BM22: 0.75
C23: Retail | E23: {=VLOOKUP($E$8:$BM$8,Assumptions!$B$47:$F$58,_xlfn.XMATCH('Financial Model'!$C23,Assumptions!$B$46:$F$46))} -> 0.75 | F23: 0.8 | G23: 0.85 | H23: 0.95 | I23: 1.1 | J23: 1.2 | K23: 0.9 | L23: 0.85 | M23: 1 | N23: 1.05 | O23: 1.2 | P23: 1.35 | Q23: 0.75 | R23: 0.8 | S23: 0.85 | T23: 0.95 | U23: 1.1 | V23: 1.2 | W23: 0.9 | X23: 0.85 | Y23: 1 | Z23: 1.05 | AA23: 1.2 | AB23: 1.35 | AC23: 0.75 | AD23: 0.8 | AE23: 0.85 | AF23: 0.95 | AG23: 1.1 | AH23: 1.2 | AI23: 0.9 | AJ23: 0.85 | AK23: 1 | AL23: 1.05 | AM23: 1.2 | AN23: 1.35 | AO23: 0.75 | AP23: 0.8 | AQ23: 0.85 | AR23: 0.95 | AS23: 1.1 | AT23: 1.2 | AU23: 0.9 | AV23: 0.85 | AW23: 1 | AX23: 1.05 | AY23: 1.2 | AZ23: 1.35 | BA23: 0.75 | BB23: 0.8 | BC23: 0.85 | BD23: 0.95 | BE23: 1.1 | BF23: 1.2 | BG23: 0.9 | BH23: 0.85 | BI23: 1 | BJ23: 1.05 | BK23: 1.2 | BL23: 1.35 | BM23: 0.75
C24: Retail | E24: {=VLOOKUP($E$8:$BM$8,Assumptions!$B$47:$F$58,_xlfn.XMATCH('Financial Model'!$C24,Assumptions!$B$46:$F$46))} -> 0.75 | F24: 0.8 | G24: 0.85 | H24: 0.95 | I24: 1.1 | J24: 1.2 | K24: 0.9 | L24: 0.85 | M24: 1 | N24: 1.05 | O24: 1.2 | P24: 1.35 | Q24: 0.75 | R24: 0.8 | S24: 0.85 | T24: 0.95 | U24: 1.1 | V24: 1.2 | W24: 0.9 | X24: 0.85 | Y24: 1 | Z24: 1.05 | AA24: 1.2 | AB24: 1.35 | AC24: 0.75 | AD24: 0.8 | AE24: 0.85 | AF24: 0.95 | AG24: 1.1 | AH24: 1.2 | AI24: 0.9 | AJ24: 0.85 | AK24: 1 | AL24: 1.05 | AM24: 1.2 | AN24: 1.35 | AO24: 0.75 | AP24: 0.8 | AQ24: 0.85 | AR24: 0.95 | AS24: 1.1 | AT24: 1.2 | AU24: 0.9 | AV24: 0.85 | AW24: 1 | AX24: 1.05 | AY24: 1.2 | AZ24: 1.35 | BA24: 0.75 | BB24: 0.8 | BC24: 0.85 | BD24: 0.95 | BE24: 1.1 | BF24: 1.2 | BG24: 0.9 | BH24: 0.85 | BI24: 1 | BJ24: 1.05 | BK24: 1.2 | BL24: 1.35 | BM24: 0.75
B26: Client Volume Growth
C28: {=cust} -> Michael’s Market Goods | D28: =Assumptions!E25 -> 375000 | E28: {=(1+(_xlfn.XLOOKUP(E$11,Assumptions!$B$35:$H$35,_xlfn.XLOOKUP($C28,Assumptions!$B$36:$B$41,Assumptions!$B$36:$H$41),,-1)))*$D28} -> 401250 | F28: {=(1+(_xlfn.XLOOKUP(F$11,Assumptions!$B$35:$H$35,_xlfn.XLOOKUP($C28,Assumptions!$B$36:$B$41,Assumptions!$B$36:$H$41),,-1)))*$D28} -> 401250 | G28: {=(1+(_xlfn.XLOOKUP(G$11,Assumptions!$B$35:$H$35,_xlfn.XLOOKUP($C28,Assumptions!$B$36:$B$41,Assumptions!$B$36:$H$41),,-1)))*$D28} -> 401250 | H28: {=(1+(_xlfn.XLOOKUP(H$11,Assumptions!$B$35:$H$35,_xlfn.XLOOKUP($C28,Assumptions!$B$36:$B$41,Assumptions!$B$36:$H$41),,-1)))*$D28} -> 401250 | I28: {=(1+(_xlfn.XLOOKUP(I$11,Assumptions!$B$35:$H$35,_xlfn.XLOOKUP($C28,Assumptions!$B$36:$B$41,Assumptions!$B$36:$H$41),,-1)))*$D28} -> 401250 | J28: {=(1+(_xlfn.XLOOKUP(J$11,Assumptions!$B$35:$H$35,_xlfn.XLOOKUP($C28,Assumptions!$B$36:$B$41,Assumptions!$B$36:$H$41),,-1)))*$D28} -> 401250 | K28: {=(1+(_xlfn.XLOOKUP(K$11,Assumptions!$B$35:$H$35,_xlfn.XLOOKUP($C28,Assumptions!$B$36:$B$41,Assumptions!$B$36:$H$41),,-1)))*$D28} -> 401250 | L28: {=(1+(_xlfn.XLOOKUP(L$11,Assumptions!$B$35:$H$35,_xlfn.XLOOKUP($C28,Assumptions!$B$36:$B$41,Assumptions!$B$36:$H$41),,-1)))*$D28} -> 401250 | ... BM28: {=(1+(_xlfn.XLOOKUP(BM$11,Assumptions!$B$35:$H$35,_xlfn.XLOOKUP($C28,Assumptions!$B$36:$B$41,Assumptions!$B$36:$H$41),,-1)))*$D28} -> 382500 | BN28: {=_xlfn.XLOOKUP(BN$11,Assumptions!$B$35:$H$35,_xlfn.XLOOKUP($C28,Assumptions!$B$36:$B$41,Assumptions!$B$36:$H$41))} -> 0 | BO28: {=_xlfn.XLOOKUP(BO$11,Assumptions!$B$35:$H$35,_xlfn.XLOOKUP($C28,Assumptions!$B$36:$B$41,Assumptions!$B$36:$H$41))} -> 0 | BP28: {=_xlfn.XLOOKUP(BP$11,Assumptions!$B$35:$H$35,_xlfn.XLOOKUP($C28,Assumptions!$B$36:$B$41,Assumptions!$B$36:$H$41))} -> 0 | BQ28: {=_xlfn.XLOOKUP(BQ$11,Assumptions!$B$35:$H$35,_xlfn.XLOOKUP($C28,Assumptions!$B$36:$B$41,Assumptions!$B$36:$H$41))} -> 0 | BR28: {=_xlfn.XLOOKUP(BR$11,Assumptions!$B$35:$H$35,_xlfn.XLOOKUP($C28,Assumptions!$B$36:$B$41,Assumptions!$B$36:$H$41))} -> 0 | BS28: {=_xlfn.XLOOKUP(BS$11,Assumptions!$B$35:$H$35,_xlfn.XLOOKUP($C28,Assumptions!$B$36:$B$41,Assumptions!$B$36:$H$41))} -> 0 | BT28: {=_xlfn.XLOOKUP(BT$11,Assumptions!$B$35:$H$35,_xlfn.XLOOKUP($C28,Assumptions!$B$36:$B$41,Assumptions!$B$36:$H$41))} -> 0 | BU28: {=_xlfn.XLOOKUP(BU$11,Assumptions!$B$35:$H$35,_xlfn.XLOOKUP($C28,Assumptions!$B$36:$B$41,Assumptions!$B$36:$H$41))} -> 0 | ... XFD28: {=_xlfn.XLOOKUP(XFD$11,Assumptions!$B$35:$H$35,_xlfn.XLOOKUP($C28,Assumptions!$B$36:$B$41,Assumptions!$B$36:$H$41))} -> 0
C29: Andrew Digital Commerce | D29: =Assumptions!E26 -> 450000 | E29: {=(1+(_xlfn.XLOOKUP(E$11,Assumptions!$B$35:$H$35,_xlfn.XLOOKUP($C29,Assumptions!$B$36:$B$41,Assumptions!$B$36:$H$41),,-1)))*$D29} -> 504000 | F29: {=(1+(_xlfn.XLOOKUP(F$11,Assumptions!$B$35:$H$35,_xlfn.XLOOKUP($C29,Assumptions!$B$36:$B$41,Assumptions!$B$36:$H$41),,-1)))*$D29} -> 504000 | G29: {=(1+(_xlfn.XLOOKUP(G$11,Assumptions!$B$35:$H$35,_xlfn.XLOOKUP($C29,Assumptions!$B$36:$B$41,Assumptions!$B$36:$H$41),,-1)))*$D29} -> 504000 | H29: {=(1+(_xlfn.XLOOKUP(H$11,Assumptions!$B$35:$H$35,_xlfn.XLOOKUP($C29,Assumptions!$B$36:$B$41,Assumptions!$B$36:$H$41),,-1)))*$D29} -> 504000 | I29: {=(1+(_xlfn.XLOOKUP(I$11,Assumptions!$B$35:$H$35,_xlfn.XLOOKUP($C29,Assumptions!$B$36:$B$41,Assumptions!$B$36:$H$41),,-1)))*$D29} -> 504000 | J29: {=(1+(_xlfn.XLOOKUP(J$11,Assumptions!$B$35:$H$35,_xlfn.XLOOKUP($C29,Assumptions!$B$36:$B$41,Assumptions!$B$36:$H$41),,-1)))*$D29} -> 504000 | K29: {=(1+(_xlfn.XLOOKUP(K$11,Assumptions!$B$35:$H$35,_xlfn.XLOOKUP($C29,Assumptions!$B$36:$B$41,Assumptions!$B$36:$H$41),,-1)))*$D29} -> 504000 | L29: {=(1+(_xlfn.XLOOKUP(L$11,Assumptions!$B$35:$H$35,_xlfn.XLOOKUP($C29,Assumptions!$B$36:$B$41,Assumptions!$B$36:$H$41),,-1)))*$D29} -> 504000 | ... BM29: {=(1+(_xlfn.XLOOKUP(BM$11,Assumptions!$B$35:$H$35,_xlfn.XLOOKUP($C29,Assumptions!$B$36:$B$41,Assumptions!$B$36:$H$41),,-1)))*$D29} -> 450000
C30: Anup Industrial Systems | D30: =Assumptions!E27 -> 225000 | E30: {=(1+(_xlfn.XLOOKUP(E$11,Assumptions!$B$35:$H$35,_xlfn.XLOOKUP($C30,Assumptions!$B$36:$B$41,Assumptions!$B$36:$H$41),,-1)))*$D30} -> 227250 | F30: {=(1+(_xlfn.XLOOKUP(F$11,Assumptions!$B$35:$H$35,_xlfn.XLOOKUP($C30,Assumptions!$B$36:$B$41,Assumptions!$B$36:$H$41),,-1)))*$D30} -> 227250 | G30: {=(1+(_xlfn.XLOOKUP(G$11,Assumptions!$B$35:$H$35,_xlfn.XLOOKUP($C30,Assumptions!$B$36:$B$41,Assumptions!$B$36:$H$41),,-1)))*$D30} -> 227250 | H30: {=(1+(_xlfn.XLOOKUP(H$11,Assumptions!$B$35:$H$35,_xlfn.XLOOKUP($C30,Assumptions!$B$36:$B$41,Assumptions!$B$36:$H$41),,-1)))*$D30} -> 227250 | I30: {=(1+(_xlfn.XLOOKUP(I$11,Assumptions!$B$35:$H$35,_xlfn.XLOOKUP($C30,Assumptions!$B$36:$B$41,Assumptions!$B$36:$H$41),,-1)))*$D30} -> 227250 | J30: {=(1+(_xlfn.XLOOKUP(J$11,Assumptions!$B$35:$H$35,_xlfn.XLOOKUP($C30,Assumptions!$B$36:$B$41,Assumptions!$B$36:$H$41),,-1)))*$D30} -> 227250 | K30: {=(1+(_xlfn.XLOOKUP(K$11,Assumptions!$B$35:$H$35,_xlfn.XLOOKUP($C30,Assumptions!$B$36:$B$41,Assumptions!$B$36:$H$41),,-1)))*$D30} -> 227250 | L30: {=(1+(_xlfn.XLOOKUP(L$11,Assumptions!$B$35:$H$35,_xlfn.XLOOKUP($C30,Assumptions!$B$36:$B$41,Assumptions!$B$36:$H$41),,-1)))*$D30} -> 227250 | ... BM30: {=(1+(_xlfn.XLOOKUP(BM$11,Assumptions!$B$35:$H$35,_xlfn.XLOOKUP($C30,Assumptions!$B$36:$B$41,Assumptions!$B$36:$H$41),,-1)))*$D30} -> 221625
C31: Joseph Retail Group | D31: =Assumptions!E28 -> 300000 | E31: {=(1+(_xlfn.XLOOKUP(E$11,Assumptions!$B$35:$H$35,_xlfn.XLOOKUP($C31,Assumptions!$B$36:$B$41,Assumptions!$B$36:$H$41),,-1)))*$D31} -> 276000 | F31: {=(1+(_xlfn.XLOOKUP(F$11,Assumptions!$B$35:$H$35,_xlfn.XLOOKUP($C31,Assumptions!$B$36:$B$41,Assumptions!$B$36:$H$41),,-1)))*$D31} -> 276000 | G31: {=(1+(_xlfn.XLOOKUP(G$11,Assumptions!$B$35:$H$35,_xlfn.XLOOKUP($C31,Assumptions!$B$36:$B$41,Assumptions!$B$36:$H$41),,-1)))*$D31} -> 276000 | H31: {=(1+(_xlfn.XLOOKUP(H$11,Assumptions!$B$35:$H$35,_xlfn.XLOOKUP($C31,Assumptions!$B$36:$B$41,Assumptions!$B$36:$H$41),,-1)))*$D31} -> 276000 | I31: {=(1+(_xlfn.XLOOKUP(I$11,Assumptions!$B$35:$H$35,_xlfn.XLOOKUP($C31,Assumptions!$B$36:$B$41,Assumptions!$B$36:$H$41),,-1)))*$D31} -> 276000 | J31: {=(1+(_xlfn.XLOOKUP(J$11,Assumptions!$B$35:$H$35,_xlfn.XLOOKUP($C31,Assumptions!$B$36:$B$41,Assumptions!$B$36:$H$41),,-1)))*$D31} -> 276000 | K31: {=(1+(_xlfn.XLOOKUP(K$11,Assumptions!$B$35:$H$35,_xlfn.XLOOKUP($C31,Assumptions!$B$36:$B$41,Assumptions!$B$36:$H$41),,-1)))*$D31} -> 276000 | L31: {=(1+(_xlfn.XLOOKUP(L$11,Assumptions!$B$35:$H$35,_xlfn.XLOOKUP($C31,Assumptions!$B$36:$B$41,Assumptions!$B$36:$H$41),,-1)))*$D31} -> 276000 | ... BM31: {=(1+(_xlfn.XLOOKUP(BM$11,Assumptions!$B$35:$H$35,_xlfn.XLOOKUP($C31,Assumptions!$B$36:$B$41,Assumptions!$B$36:$H$41),,-1)))*$D31} -> 279000
C32: Dim Collective | D32: =Assumptions!E29 -> 125000 | E32: {=(1+(_xlfn.XLOOKUP(E$11,Assumptions!$B$35:$H$35,_xlfn.XLOOKUP($C32,Assumptions!$B$36:$B$41,Assumptions!$B$36:$H$41),,-1)))*$D32} -> 162500 | F32: {=(1+(_xlfn.XLOOKUP(F$11,Assumptions!$B$35:$H$35,_xlfn.XLOOKUP($C32,Assumptions!$B$36:$B$41,Assumptions!$B$36:$H$41),,-1)))*$D32} -> 162500 | G32: {=(1+(_xlfn.XLOOKUP(G$11,Assumptions!$B$35:$H$35,_xlfn.XLOOKUP($C32,Assumptions!$B$36:$B$41,Assumptions!$B$36:$H$41),,-1)))*$D32} -> 162500 | H32: {=(1+(_xlfn.XLOOKUP(H$11,Assumptions!$B$35:$H$35,_xlfn.XLOOKUP($C32,Assumptions!$B$36:$B$41,Assumptions!$B$36:$H$41),,-1)))*$D32} -> 162500 | I32: {=(1+(_xlfn.XLOOKUP(I$11,Assumptions!$B$35:$H$35,_xlfn.XLOOKUP($C32,Assumptions!$B$36:$B$41,Assumptions!$B$36:$H$41),,-1)))*$D32} -> 162500 | J32: {=(1+(_xlfn.XLOOKUP(J$11,Assumptions!$B$35:$H$35,_xlfn.XLOOKUP($C32,Assumptions!$B$36:$B$41,Assumptions!$B$36:$H$41),,-1)))*$D32} -> 162500 | K32: {=(1+(_xlfn.XLOOKUP(K$11,Assumptions!$B$35:$H$35,_xlfn.XLOOKUP($C32,Assumptions!$B$36:$B$41,Assumptions!$B$36:$H$41),,-1)))*$D32} -> 162500 | L32: {=(1+(_xlfn.XLOOKUP(L$11,Assumptions!$B$35:$H$35,_xlfn.XLOOKUP($C32,Assumptions!$B$36:$B$41,Assumptions!$B$36:$H$41),,-1)))*$D32} -> 162500 | ... BM32: {=(1+(_xlfn.XLOOKUP(BM$11,Assumptions!$B$35:$H$35,_xlfn.XLOOKUP($C32,Assumptions!$B$36:$B$41,Assumptions!$B$36:$H$41),,-1)))*$D32} -> 130000
C33: Tim Forward Brands | D33: =Assumptions!E30 -> 250000 | E33: {=(1+(_xlfn.XLOOKUP(E$11,Assumptions!$B$35:$H$35,_xlfn.XLOOKUP($C33,Assumptions!$B$36:$B$41,Assumptions!$B$36:$H$41),,-1)))*$D33} -> 250000 | F33: {=(1+(_xlfn.XLOOKUP(F$11,Assumptions!$B$35:$H$35,_xlfn.XLOOKUP($C33,Assumptions!$B$36:$B$41,Assumptions!$B$36:$H$41),,-1)))*$D33} -> 250000 | G33: {=(1+(_xlfn.XLOOKUP(G$11,Assumptions!$B$35:$H$35,_xlfn.XLOOKUP($C33,Assumptions!$B$36:$B$41,Assumptions!$B$36:$H$41),,-1)))*$D33} -> 250000 | H33: {=(1+(_xlfn.XLOOKUP(H$11,Assumptions!$B$35:$H$35,_xlfn.XLOOKUP($C33,Assumptions!$B$36:$B$41,Assumptions!$B$36:$H$41),,-1)))*$D33} -> 250000 | I33: {=(1+(_xlfn.XLOOKUP(I$11,Assumptions!$B$35:$H$35,_xlfn.XLOOKUP($C33,Assumptions!$B$36:$B$41,Assumptions!$B$36:$H$41),,-1)))*$D33} -> 250000 | J33: {=(1+(_xlfn.XLOOKUP(J$11,Assumptions!$B$35:$H$35,_xlfn.XLOOKUP($C33,Assumptions!$B$36:$B$41,Assumptions!$B$36:$H$41),,-1)))*$D33} -> 250000 | K33: {=(1+(_xlfn.XLOOKUP(K$11,Assumptions!$B$35:$H$35,_xlfn.XLOOKUP($C33,Assumptions!$B$36:$B$41,Assumptions!$B$36:$H$41),,-1)))*$D33} -> 250000 | L33: {=(1+(_xlfn.XLOOKUP(L$11,Assumptions!$B$35:$H$35,_xlfn.XLOOKUP($C33,Assumptions!$B$36:$B$41,Assumptions!$B$36:$H$41),,-1)))*$D33} -> 250000 | ... BM33: {=(1+(_xlfn.XLOOKUP(BM$11,Assumptions!$B$35:$H$35,_xlfn.XLOOKUP($C33,Assumptions!$B$36:$B$41,Assumptions!$B$36:$H$41),,-1)))*$D33} -> 260000

Sheet Model
B2: Tom Forward Brands Currently | C2: ='Dashboard Summary'!D4 -> Off
B4: X-Logistic Services (XLS) - 5 Year Financial Projection
C7: Period Number | G7: {=_xlfn.SEQUENCE(,62,0)} -> 0 | H7: 1 | I7: 2 | J7: 3 | K7: 4 | L7: 5 | M7: 6 | N7: 7 | O7: 8 | P7: 9 | Q7: 10 | R7: 11 | S7: 12 | T7: 13 | U7: 14 | V7: 15 | W7: 16 | X7: 17 | Y7: 18 | Z7: 19 | AA7: 20 | AB7: 21 | AC7: 22 | AD7: 23 | AE7: 24 | AF7: 25 | AG7: 26 | AH7: 27 | AI7: 28 | AJ7: 29 | AK7: 30 | AL7: 31 | AM7: 32 | AN7: 33 | AO7: 34 | AP7: 35 | AQ7: 36 | AR7: 37 | AS7: 38 | AT7: 39 | AU7: 40 | AV7: 41 | AW7: 42 | AX7: 43 | AY7: 44 | AZ7: 45 | BA7: 46 | BB7: 47 | BC7: 48 | BD7: 49 | BE7: 50 | BF7: 51 | BG7: 52 | BH7: 53 | BI7: 54 | BJ7: 55 | BK7: 56 | BL7: 57 | BM7: 58 | BN7: 59 | BO7: 60 | BP7: 61
C8: Period End | G8: =EOMONTH(DATE(2025,12,1),G7) -> 46022 | H8: =EOMONTH(DATE(2025,12,1),H7) -> 46053 | I8: =EOMONTH(DATE(2025,12,1),I7) -> 46081 | J8: =EOMONTH(DATE(2025,12,1),J7) -> 46112 | K8: =EOMONTH(DATE(2025,12,1),K7) -> 46142 | L8: =EOMONTH(DATE(2025,12,1),L7) -> 46173 | M8: =EOMONTH(DATE(2025,12,1),M7) -> 46203 | N8: =EOMONTH(DATE(2025,12,1),N7) -> 46234 | ... BP8: =EOMONTH(DATE(2025,12,1),BP7) -> 47879
C9: Month | G9: {=MONTH(G8:BP8)} -> 12 | H9: 1 | I9: 2 | J9: 3 | K9: 4 | L9: 5 | M9: 6 | N9: 7 | O9: 8 | P9: 9 | Q9: 10 | R9: 11 | S9: 12 | T9: 1 | U9: 2 | V9: 3 | W9: 4 | X9: 5 | Y9: 6 | Z9: 7 | AA9: 8 | AB9: 9 | AC9: 10 | AD9: 11 | AE9: 12 | AF9: 1 | AG9: 2 | AH9: 3 | AI9: 4 | AJ9: 5 | AK9: 6 | AL9: 7 | AM9: 8 | AN9: 9 | AO9: 10 | AP9: 11 | AQ9: 12 | AR9: 1 | AS9: 2 | AT9: 3 | AU9: 4 | AV9: 5 | AW9: 6 | AX9: 7 | AY9: 8 | AZ9: 9 | BA9: 10 | BB9: 11 | BC9: 12 | BD9: 1 | BE9: 2 | BF9: 3 | BG9: 4 | BH9: 5 | BI9: 6 | BJ9: 7 | BK9: 8 | BL9: 9 | BM9: 10 | BN9: 11 | BO9: 12 | BP9: 1
C10: Year | G10: {=YEAR(G8:BP8)} -> 2025 | H10: 2026 | I10: 2026 | J10: 2026 | K10: 2026 | L10: 2026 | M10: 2026 | N10: 2026 | O10: 2026 | P10: 2026 | Q10: 2026 | R10: 2026 | S10: 2026 | T10: 2027 | U10: 2027 | V10: 2027 | W10: 2027 | X10: 2027 | Y10: 2027 | Z10: 2027 | AA10: 2027 | AB10: 2027 | AC10: 2027 | AD10: 2027 | AE10: 2027 | AF10: 2028 | AG10: 2028 | AH10: 2028 | AI10: 2028 | AJ10: 2028 | AK10: 2028 | AL10: 2028 | AM10: 2028 | AN10: 2028 | AO10: 2028 | AP10: 2028 | AQ10: 2028 | AR10: 2029 | AS10: 2029 | AT10: 2029 | AU10: 2029 | AV10: 2029 | AW10: 2029 | AX10: 2029 | AY10: 2029 | AZ10: 2029 | BA10: 2029 | BB10: 2029 | BC10: 2029 | BD10: 2030 | BE10: 2030 | BF10: 2030 | BG10: 2030 | BH10: 2030 | BI10: 2030 | BJ10: 2030 | BK10: 2030 | BL10: 2030 | BM10: 2030 | BN10: 2030 | BO10: 2030 | BP10: 2031
B13: P&L Statement
C20: Net Revenue | D20: =SUM(H20:BO20) -> 1.2415581e+08 | F20: [$] | H20: {=_xlfn.ANCHORARRAY(H197)} -> 1061089 | I20: 1110288.3 | J20: 1221309.1 | K20: 1354238.9 | L20: 1483298.3 | M20: 1409043.1 | N20: 1256633.2 | O20: 1415401.8 | P20: 1606767.1 | Q20: 1840443.4 | R20: 2240213.9 | S20: 1924048.3 | T20: 1318859.8 | U20: 1371272.9 | V20: 1490747 | W20: 1633609 | X20: 1772207.4 | Y20: 1693530.1 | Z20: 1531875 | AA20: 1703155.7 | AB20: 1908451.3 | AC20: 2162319.1 | AD20: 2596936.1 | AE20: 2245744.6 | AF20: 1581562.3 | AG20: 1637222.6 | AH20: 1763589.8 | AI20: 1915171.5 | AJ20: 2062321.9 | AK20: 1979402.3 | AL20: 1808806.8 | AM20: 1989059.9 | AN20: 2205348.3 | AO20: 2473558 | AP20: 2932311.2 | AQ20: 2549563 | AR20: 1840000.9 | AS20: 1897975.4 | AT20: 2029022.5 | AU20: 2186585.4 | AV20: 2339620.2 | AW20: 2253840 | AX20: 2077247.9 | AY20: 2263443.1 | AZ20: 2487085.8 | BA20: 2764705.7 | BB20: 3239126.5 | BC20: 2840849.8 | BD20: 2111597 | BE20: 2171564.6 | BF20: 2306914.9 | BG20: 2469906.5 | BH20: 2628248.6 | BI20: 2539906.3 | BJ20: 2358005.4 | BK20: 2549839.4 | BL20: 2780255.6 | BM20: 3066997.7 | BN20: 3556761 | BO20: 3146909.8 | BP20: 0
C21: COGS (Cost of Goods Sold) | D21: =SUM(H21:BO21) -> -64552280 | F21: [$] | H21: {=-_xlfn.ANCHORARRAY(H352)} -> -801649.18 | I21: -802195.51 | J21: -821967.12 | K21: -897137.9 | L21: -970470.07 | M21: -926125.73 | N21: -814733.39 | O21: -898439.02 | P21: -1014312.2 | Q21: -1142816.1 | R21: -1378488 | S21: -1198947.2 | T21: -834927.38 | U21: -835504.5 | V21: -879418.04 | W21: -959966.86 | X21: -1038406 | Y21: -991100.93 | Z21: -872512.54 | AA21: -962746.76 | AB21: -1086654 | AC21: -1226058.1 | AD21: -1482046.9 | AE21: -1282310.3 | AF21: -891261.67 | AG21: -891871.54 | AH21: -919672.22 | AI21: -1004968.5 | AJ21: -1088061.1 | AK21: -1037969.2 | AL21: -912613.72 | AM21: -1007384.3 | AN21: -1137649.2 | AO21: -1284734.8 | AP21: -1554705.1 | AQ21: -1336740.9 | AR21: -931679.15 | AS21: -932311.82 | AT21: -946630.76 | AU21: -1035139.2 | AV21: -1121387.3 | AW21: -1069354.9 | AX21: -939404.31 | AY21: -1037120.5 | AZ21: -1171588.5 | BA21: -1323654 | BB21: -1602623.7 | BC21: -1375582.3 | BD21: -964278.58 | BE21: -964930.8 | BF21: -972503.32 | BG21: -1063938.7 | BH21: -1153039.2 | BI21: -1099280.9 | BJ21: -966296.63 | BK21: -1065794.6 | BL21: -1204136.2 | BM21: -1361062.4 | BN21: -1648892.3 | BO21: -1415084.5
C22: Gross Profit | D22: =D20+D21 -> 59603530 | H22: {=+H20:BO20+H21:BO21} -> 259439.86 | I22: 308092.75 | J22: 399342.02 | K22: 457100.97 | L22: 512828.23 | M22: 482917.39 | N22: 441899.76 | O22: 516962.77 | P22: 592454.93 | Q22: 697627.3 | R22: 861725.93 | S22: 725101.18 | T22: 483932.42 | U22: 535768.41 | V22: 611328.99 | W22: 673642.12 | X22: 733801.44 | Y22: 702429.19 | Z22: 659362.44 | AA22: 740408.98 | AB22: 821797.29 | AC22: 936260.93 | AD22: 1114889.3 | AE22: 963434.23 | AF22: 690300.66 | AG22: 745351.07 | AH22: 843917.58 | AI22: 910203.06 | AJ22: 974260.8 | AK22: 941433.06 | AL22: 896193.11 | AM22: 981675.55 | AN22: 1067699.1 | AO22: 1188823.2 | AP22: 1377606.1 | AQ22: 1212822.1 | AR22: 908321.73 | AS22: 965663.62 | AT22: 1082391.8 | AU22: 1151446.2 | AV22: 1218232.8 | AW22: 1184485 | AX22: 1137843.6 | AY22: 1226322.6 | AZ22: 1315497.2 | BA22: 1441051.6 | BB22: 1636502.8 | BC22: 1465267.5 | BD22: 1147318.4 | BE22: 1206633.8 | BF22: 1334411.6 | BG22: 1405967.8 | BH22: 1475209.5 | BI22: 1440625.3 | BJ22: 1391708.8 | BK22: 1484044.8 | BL22: 1576119.3 | BM22: 1705935.4 | BN22: 1907868.7 | BO22: 1731825.3
C24: SG&A (Sales, General & Administrative Expense) | D24: =SUM(H24:BO24) -> -3981851.9 | F24: [$] | H24: {=-_xlfn.ANCHORARRAY(H354)} -> -62500 | I24: -62500 | J24: -62500 | K24: -62500 | L24: -62500 | M24: -62500 | N24: -62500 | O24: -62500 | P24: -62500 | Q24: -62500 | R24: -62500 | S24: -62500 | T24: -64375 | U24: -64375 | V24: -64375 | W24: -64375 | X24: -64375 | Y24: -64375 | Z24: -64375 | AA24: -64375 | AB24: -64375 | AC24: -64375 | AD24: -64375 | AE24: -64375 | AF24: -66306.25 | AG24: -66306.25 | AH24: -66306.25 | AI24: -66306.25 | AJ24: -66306.25 | AK24: -66306.25 | AL24: -66306.25 | AM24: -66306.25 | AN24: -66306.25 | AO24: -66306.25 | AP24: -66306.25 | AQ24: -66306.25 | AR24: -68295.438 | AS24: -68295.438 | AT24: -68295.438 | AU24: -68295.438 | AV24: -68295.438 | AW24: -68295.438 | AX24: -68295.438 | AY24: -68295.438 | AZ24: -68295.438 | BA24: -68295.438 | BB24: -68295.438 | BC24: -68295.438 | BD24: -70344.301 | BE24: -70344.301 | BF24: -70344.301 | BG24: -70344.301 | BH24: -70344.301 | BI24: -70344.301 | BJ24: -70344.301 | BK24: -70344.301 | BL24: -70344.301 | BM24: -70344.301 | BN24: -70344.301 | BO24: -70344.301
C26: EBITDA | D26: =SUM(H26:BO26) -> 55621678 | H26: {=+H22:BO22+H24:BO24} -> 196939.86 | I26: 245592.75 | J26: 336842.02 | K26: 394600.97 | L26: 450328.23 | M26: 420417.39 | N26: 379399.76 | O26: 454462.77 | P26: 529954.93 | Q26: 635127.3 | R26: 799225.93 | S26: 662601.18 | T26: 419557.42 | U26: 471393.41 | V26: 546953.99 | W26: 609267.12 | X26: 669426.44 | Y26: 638054.19 | Z26: 594987.44 | AA26: 676033.98 | AB26: 757422.29 | AC26: 871885.93 | AD26: 1050514.3 | AE26: 899059.23 | AF26: 623994.41 | AG26: 679044.82 | AH26: 777611.33 | AI26: 843896.81 | AJ26: 907954.55 | AK26: 875126.81 | AL26: 829886.86 | AM26: 915369.3 | AN26: 1001392.8 | AO26: 1122516.9 | AP26: 1311299.9 | AQ26: 1146515.9 | AR26: 840026.29 | AS26: 897368.18 | AT26: 1014096.3 | AU26: 1083150.8 | AV26: 1149937.4 | AW26: 1116189.6 | AX26: 1069548.2 | AY26: 1158027.1 | AZ26: 1247201.8 | BA26: 1372756.2 | BB26: 1568207.4 | BC26: 1396972.1 | BD26: 1076974.1 | BE26: 1136289.5 | BF26: 1264067.3 | BG26: 1335623.5 | BH26: 1404865.2 | BI26: 1370281 | BJ26: 1321364.5 | BK26: 1413700.5 | BL26: 1505775 | BM26: 1635591.1 | BN26: 1837524.4 | BO26: 1661481
B28: Schedules and Supporting Calculations
B29: 1 Time Schedules
C31: Inflation Index | D31: 0.03 | F31: [coef] | H31: {=(1+Assumptions!D10)^(H10:BO10-$H$10)} -> 1 | I31: 1 | J31: 1 | K31: 1 | L31: 1 | M31: 1 | N31: 1 | O31: 1 | P31: 1 | Q31: 1 | R31: 1 | S31: 1 | T31: 1.03 | U31: 1.03 | V31: 1.03 | W31: 1.03 | X31: 1.03 | Y31: 1.03 | Z31: 1.03 | AA31: 1.03 | AB31: 1.03 | AC31: 1.03 | AD31: 1.03 | AE31: 1.03 | AF31: 1.0609 | AG31: 1.0609 | AH31: 1.0609 | AI31: 1.0609 | AJ31: 1.0609 | AK31: 1.0609 | AL31: 1.0609 | AM31: 1.0609 | AN31: 1.0609 | AO31: 1.0609 | AP31: 1.0609 | AQ31: 1.0609 | AR31: 1.092727 | AS31: 1.092727 | AT31: 1.092727 | AU31: 1.092727 | AV31: 1.092727 | AW31: 1.092727 | AX31: 1.092727 | AY31: 1.092727 | AZ31: 1.092727 | BA31: 1.092727 | BB31: 1.092727 | BC31: 1.092727 | BD31: 1.1255088 | BE31: 1.1255088 | BF31: 1.1255088 | BG31: 1.1255088 | BH31: 1.1255088 | BI31: 1.1255088 | BJ31: 1.1255088 | BK31: 1.1255088 | BL31: 1.1255088 | BM31: 1.1255088 | BN31: 1.1255088 | BO31: 1.1255088
B34: Customer Active Status | D34: =Assumptions!I24 -> Contract Active | E34: =Assumptions!D24 -> Starting Month
C35: {=cust} -> Michael’s Market Goods | D35: {=active} -> 1 | E35: {=month} -> 1 | F35: [flg] | G35: {=IF(_xlfn.ANCHORARRAY(D35)=1,IF(_xlfn.ANCHORARRAY(G7)>=_xlfn.ANCHORARRAY(E35),1,0),0)} -> 0 | H35: 1 | I35: 1 | J35: 1 | K35: 1 | L35: 1 | M35: 1 | N35: 1 | O35: 1 | P35: 1 | Q35: 1 | R35: 1 | S35: 1 | T35: 1 | U35: 1 | V35: 1 | W35: 1 | X35: 1 | Y35: 1 | Z35: 1 | AA35: 1 | AB35: 1 | AC35: 1 | AD35: 1 | AE35: 1 | AF35: 1 | AG35: 1 | AH35: 1 | AI35: 1 | AJ35: 1 | AK35: 1 | AL35: 1 | AM35: 1 | AN35: 1 | AO35: 1 | AP35: 1 | AQ35: 1 | AR35: 1 | AS35: 1 | AT35: 1 | AU35: 1 | AV35: 1 | AW35: 1 | AX35: 1 | AY35: 1 | AZ35: 1 | BA35: 1 | BB35: 1 | BC35: 1 | BD35: 1 | BE35: 1 | BF35: 1 | BG35: 1 | BH35: 1 | BI35: 1 | BJ35: 1 | BK35: 1 | BL35: 1 | BM35: 1 | BN35: 1 | BO35: 1 | BP35: 1
C36: Andrew Digital Commerce | D36: 1 | E36: 1 | F36: [flg] | G36: 0 | H36: 1 | I36: 1 | J36: 1 | K36: 1 | L36: 1 | M36: 1 | N36: 1 | O36: 1 | P36: 1 | Q36: 1 | R36: 1 | S36: 1 | T36: 1 | U36: 1 | V36: 1 | W36: 1 | X36: 1 | Y36: 1 | Z36: 1 | AA36: 1 | AB36: 1 | AC36: 1 | AD36: 1 | AE36: 1 | AF36: 1 | AG36: 1 | AH36: 1 | AI36: 1 | AJ36: 1 | AK36: 1 | AL36: 1 | AM36: 1 | AN36: 1 | AO36: 1 | AP36: 1 | AQ36: 1 | AR36: 1 | AS36: 1 | AT36: 1 | AU36: 1 | AV36: 1 | AW36: 1 | AX36: 1 | AY36: 1 | AZ36: 1 | BA36: 1 | BB36: 1 | BC36: 1 | BD36: 1 | BE36: 1 | BF36: 1 | BG36: 1 | BH36: 1 | BI36: 1 | BJ36: 1 | BK36: 1 | BL36: 1 | BM36: 1 | BN36: 1 | BO36: 1 | BP36: 1
C37: Anup Industrial Systems | D37: 1 | E37: 1 | F37: [flg] | G37: 0 | H37: 1 | I37: 1 | J37: 1 | K37: 1 | L37: 1 | M37: 1 | N37: 1 | O37: 1 | P37: 1 | Q37: 1 | R37: 1 | S37: 1 | T37: 1 | U37: 1 | V37: 1 | W37: 1 | X37: 1 | Y37: 1 | Z37: 1 | AA37: 1 | AB37: 1 | AC37: 1 | AD37: 1 | AE37: 1 | AF37: 1 | AG37: 1 | AH37: 1 | AI37: 1 | AJ37: 1 | AK37: 1 | AL37: 1 | AM37: 1 | AN37: 1 | AO37: 1 | AP37: 1 | AQ37: 1 | AR37: 1 | AS37: 1 | AT37: 1 | AU37: 1 | AV37: 1 | AW37: 1 | AX37: 1 | AY37: 1 | AZ37: 1 | BA37: 1 | BB37: 1 | BC37: 1 | BD37: 1 | BE37: 1 | BF37: 1 | BG37: 1 | BH37: 1 | BI37: 1 | BJ37: 1 | BK37: 1 | BL37: 1 | BM37: 1 | BN37: 1 | BO37: 1 | BP37: 1
C38: Joseph Retail Group | D38: 1 | E38: 1 | F38: [flg] | G38: 0 | H38: 1 | I38: 1 | J38: 1 | K38: 1 | L38: 1 | M38: 1 | N38: 1 | O38: 1 | P38: 1 | Q38: 1 | R38: 1 | S38: 1 | T38: 1 | U38: 1 | V38: 1 | W38: 1 | X38: 1 | Y38: 1 | Z38: 1 | AA38: 1 | AB38: 1 | AC38: 1 | AD38: 1 | AE38: 1 | AF38: 1 | AG38: 1 | AH38: 1 | AI38: 1 | AJ38: 1 | AK38: 1 | AL38: 1 | AM38: 1 | AN38: 1 | AO38: 1 | AP38: 1 | AQ38: 1 | AR38: 1 | AS38: 1 | AT38: 1 | AU38: 1 | AV38: 1 | AW38: 1 | AX38: 1 | AY38: 1 | AZ38: 1 | BA38: 1 | BB38: 1 | BC38: 1 | BD38: 1 | BE38: 1 | BF38: 1 | BG38: 1 | BH38: 1 | BI38: 1 | BJ38: 1 | BK38: 1 | BL38: 1 | BM38: 1 | BN38: 1 | BO38: 1 | BP38: 1
C39: Dim Collective | D39: 1 | E39: 1 | F39: [flg] | G39: 0 | H39: 1 | I39: 1 | J39: 1 | K39: 1 | L39: 1 | M39: 1 | N39: 1 | O39: 1 | P39: 1 | Q39: 1 | R39: 1 | S39: 1 | T39: 1 | U39: 1 | V39: 1 | W39: 1 | X39: 1 | Y39: 1 | Z39: 1 | AA39: 1 | AB39: 1 | AC39: 1 | AD39: 1 | AE39: 1 | AF39: 1 | AG39: 1 | AH39: 1 | AI39: 1 | AJ39: 1 | AK39: 1 | AL39: 1 | AM39: 1 | AN39: 1 | AO39: 1 | AP39: 1 | AQ39: 1 | AR39: 1 | AS39: 1 | AT39: 1 | AU39: 1 | AV39: 1 | AW39: 1 | AX39: 1 | AY39: 1 | AZ39: 1 | BA39: 1 | BB39: 1 | BC39: 1 | BD39: 1 | BE39: 1 | BF39: 1 | BG39: 1 | BH39: 1 | BI39: 1 | BJ39: 1 | BK39: 1 | BL39: 1 | BM39: 1 | BN39: 1 | BO39: 1 | BP39: 1
C40: Tim Forward Brands | D40: 0 | E40: 37 | F40: [flg] | G40: 0 | H40: 0 | I40: 0 | J40: 0 | K40: 0 | L40: 0 | M40: 0 | N40: 0 | O40: 0 | P40: 0 | Q40: 0 | R40: 0 | S40: 0 | T40: 0 | U40: 0 | V40: 0 | W40: 0 | X40: 0 | Y40: 0 | Z40: 0 | AA40: 0 | AB40: 0 | AC40: 0 | AD40: 0 | AE40: 0 | AF40: 0 | AG40: 0 | AH40: 0 | AI40: 0 | AJ40: 0 | AK40: 0 | AL40: 0 | AM40: 0 | AN40: 0 | AO40: 0 | AP40: 0 | AQ40: 0 | AR40: 0 | AS40: 0 | AT40: 0 | AU40: 0 | AV40: 0 | AW40: 0 | AX40: 0 | AY40: 0 | AZ40: 0 | BA40: 0 | BB40: 0 | BC40: 0 | BD40: 0 | BE40: 0 | BF40: 0 | BG40: 0 | BH40: 0 | BI40: 0 | BJ40: 0 | BK40: 0 | BL40: 0 | BM40: 0 | BN40: 0 | BO40: 0 | BP40: 0
B42: 2 Demand / Growth
B44: Seasonal Demand | D44: =Assumptions!C24 -> Segment
C45: {=cust} -> Michael’s Market Goods | D45: {=seg} -> Retail | F45: [%] | H45: {=INDEX(Assumptions!$D$47:$F$58,Model!H9:BP9,_xlfn.XMATCH(_xlfn.ANCHORARRAY(D45),Assumptions!D46:F46))} -> 0.75 | I45: 0.8 | J45: 0.85 | K45: 0.95 | L45: 1.1 | M45: 1.2 | N45: 0.9 | O45: 0.85 | P45: 1 | Q45: 1.05 | R45: 1.2 | S45: 1.35 | T45: 0.75 | U45: 0.8 | V45: 0.85 | W45: 0.95 | X45: 1.1 | Y45: 1.2 | Z45: 0.9 | AA45: 0.85 | AB45: 1 | AC45: 1.05 | AD45: 1.2 | AE45: 1.35 | AF45: 0.75 | AG45: 0.8 | AH45: 0.85 | AI45: 0.95 | AJ45: 1.1 | AK45: 1.2 | AL45: 0.9 | AM45: 0.85 | AN45: 1 | AO45: 1.05 | AP45: 1.2 | AQ45: 1.35 | AR45: 0.75 | AS45: 0.8 | AT45: 0.85 | AU45: 0.95 | AV45: 1.1 | AW45: 1.2 | AX45: 0.9 | AY45: 0.85 | AZ45: 1 | BA45: 1.05 | BB45: 1.2 | BC45: 1.35 | BD45: 0.75 | BE45: 0.8 | BF45: 0.85 | BG45: 0.95 | BH45: 1.1 | BI45: 1.2 | BJ45: 0.9 | BK45: 0.85 | BL45: 1 | BM45: 1.05 | BN45: 1.2 | BO45: 1.35 | BP45: 0.75
C46: Andrew Digital Commerce | D46: E-commerce | F46: [%] | H46: 0.75 | I46: 0.65 | J46: 0.7 | K46: 0.75 | L46: 0.7 | M46: 0.75 | N46: 0.7 | O46: 0.9 | P46: 1.05 | Q46: 1.1 | R46: 1.75 | S46: 2.2 | T46: 0.75 | U46: 0.65 | V46: 0.7 | W46: 0.75 | X46: 0.7 | Y46: 0.75 | Z46: 0.7 | AA46: 0.9 | AB46: 1.05 | AC46: 1.1 | AD46: 1.75 | AE46: 2.2 | AF46: 0.75 | AG46: 0.65 | AH46: 0.7 | AI46: 0.75 | AJ46: 0.7 | AK46: 0.75 | AL46: 0.7 | AM46: 0.9 | AN46: 1.05 | AO46: 1.1 | AP46: 1.75 | AQ46: 2.2 | AR46: 0.75 | AS46: 0.65 | AT46: 0.7 | AU46: 0.75 | AV46: 0.7 | AW46: 0.75 | AX46: 0.7 | AY46: 0.9 | AZ46: 1.05 | BA46: 1.1 | BB46: 1.75 | BC46: 2.2 | BD46: 0.75 | BE46: 0.65 | BF46: 0.7 | BG46: 0.75 | BH46: 0.7 | BI46: 0.75 | BJ46: 0.7 | BK46: 0.9 | BL46: 1.05 | BM46: 1.1 | BN46: 1.75 | BO46: 2.2 | BP46: 0.75
C47: Anup Industrial Systems | D47: Industrial | F47: [%] | H47: 0.95 | I47: 0.95 | J47: 1 | K47: 1 | L47: 1 | M47: 1 | N47: 0.95 | O47: 0.9 | P47: 1.1 | Q47: 1.1 | R47: 1.05 | S47: 1 | T47: 0.95 | U47: 0.95 | V47: 1 | W47: 1 | X47: 1 | Y47: 1 | Z47: 0.95 | AA47: 0.9 | AB47: 1.1 | AC47: 1.1 | AD47: 1.05 | AE47: 1 | AF47: 0.95 | AG47: 0.95 | AH47: 1 | AI47: 1 | AJ47: 1 | AK47: 1 | AL47: 0.95 | AM47: 0.9 | AN47: 1.1 | AO47: 1.1 | AP47: 1.05 | AQ47: 1 | AR47: 0.95 | AS47: 0.95 | AT47: 1 | AU47: 1 | AV47: 1 | AW47: 1 | AX47: 0.95 | AY47: 0.9 | AZ47: 1.1 | BA47: 1.1 | BB47: 1.05 | BC47: 1 | BD47: 0.95 | BE47: 0.95 | BF47: 1 | BG47: 1 | BH47: 1 | BI47: 1 | BJ47: 0.95 | BK47: 0.9 | BL47: 1.1 | BM47: 1.1 | BN47: 1.05 | BO47: 1 | BP47: 0.95
C48: Joseph Retail Group | D48: Retail | F48: [%] | H48: 0.75 | I48: 0.8 | J48: 0.85 | K48: 0.95 | L48: 1.1 | M48: 1.2 | N48: 0.9 | O48: 0.85 | P48: 1 | Q48: 1.05 | R48: 1.2 | S48: 1.35 | T48: 0.75 | U48: 0.8 | V48: 0.85 | W48: 0.95 | X48: 1.1 | Y48: 1.2 | Z48: 0.9 | AA48: 0.85 | AB48: 1 | AC48: 1.05 | AD48: 1.2 | AE48: 1.35 | AF48: 0.75 | AG48: 0.8 | AH48: 0.85 | AI48: 0.95 | AJ48: 1.1 | AK48: 1.2 | AL48: 0.9 | AM48: 0.85 | AN48: 1 | AO48: 1.05 | AP48: 1.2 | AQ48: 1.35 | AR48: 0.75 | AS48: 0.8 | AT48: 0.85 | AU48: 0.95 | AV48: 1.1 | AW48: 1.2 | AX48: 0.9 | AY48: 0.85 | AZ48: 1 | BA48: 1.05 | BB48: 1.2 | BC48: 1.35 | BD48: 0.75 | BE48: 0.8 | BF48: 0.85 | BG48: 0.95 | BH48: 1.1 | BI48: 1.2 | BJ48: 0.9 | BK48: 0.85 | BL48: 1 | BM48: 1.05 | BN48: 1.2 | BO48: 1.35 | BP48: 0.75
C49: Dim Collective | D49: Retail | F49: [%] | H49: 0.75 | I49: 0.8 | J49: 0.85 | K49: 0.95 | L49: 1.1 | M49: 1.2 | N49: 0.9 | O49: 0.85 | P49: 1 | Q49: 1.05 | R49: 1.2 | S49: 1.35 | T49: 0.75 | U49: 0.8 | V49: 0.85 | W49: 0.95 | X49: 1.1 | Y49: 1.2 | Z49: 0.9 | AA49: 0.85 | AB49: 1 | AC49: 1.05 | AD49: 1.2 | AE49: 1.35 | AF49: 0.75 | AG49: 0.8 | AH49: 0.85 | AI49: 0.95 | AJ49: 1.1 | AK49: 1.2 | AL49: 0.9 | AM49: 0.85 | AN49: 1 | AO49: 1.05 | AP49: 1.2 | AQ49: 1.35 | AR49: 0.75 | AS49: 0.8 | AT49: 0.85 | AU49: 0.95 | AV49: 1.1 | AW49: 1.2 | AX49: 0.9 | AY49: 0.85 | AZ49: 1 | BA49: 1.05 | BB49: 1.2 | BC49: 1.35 | BD49: 0.75 | BE49: 0.8 | BF49: 0.85 | BG49: 0.95 | BH49: 1.1 | BI49: 1.2 | BJ49: 0.9 | BK49: 0.85 | BL49: 1 | BM49: 1.05 | BN49: 1.2 | BO49: 1.35 | BP49: 0.75
C50: Tim Forward Brands | D50: Retail | F50: [%] | H50: 0.75 | I50: 0.8 | J50: 0.85 | K50: 0.95 | L50: 1.1 | M50: 1.2 | N50: 0.9 | O50: 0.85 | P50: 1 | Q50: 1.05 | R50: 1.2 | S50: 1.35 | T50: 0.75 | U50: 0.8 | V50: 0.85 | W50: 0.95 | X50: 1.1 | Y50: 1.2 | Z50: 0.9 | AA50: 0.85 | AB50: 1 | AC50: 1.05 | AD50: 1.2 | AE50: 1.35 | AF50: 0.75 | AG50: 0.8 | AH50: 0.85 | AI50: 0.95 | AJ50: 1.1 | AK50: 1.2 | AL50: 0.9 | AM50: 0.85 | AN50: 1 | AO50: 1.05 | AP50: 1.2 | AQ50: 1.35 | AR50: 0.75 | AS50: 0.8 | AT50: 0.85 | AU50: 0.95 | AV50: 1.1 | AW50: 1.2 | AX50: 0.9 | AY50: 0.85 | AZ50: 1 | BA50: 1.05 | BB50: 1.2 | BC50: 1.35 | BD50: 0.75 | BE50: 0.8 | BF50: 0.85 | BG50: 0.95 | BH50: 1.1 | BI50: 1.2 | BJ50: 0.9 | BK50: 0.85 | BL50: 1 | BM50: 1.05 | BN50: 1.2 | BO50: 1.35 | BP50: 0.75
B52: Customer YoY Growth
C53: {=cust} -> Michael’s Market Goods | F53: [%] | H53: {=INDEX(Assumptions!D36:H41,_xlfn.XMATCH(_xlfn.ANCHORARRAY(Model!C53),Assumptions!B36:B41),_xlfn.XMATCH(Model!H10:BP10-Model!G10,Assumptions!D35:H35,-1))} -> 0.07 | I53: 0.07 | J53: 0.07 | K53: 0.07 | L53: 0.07 | M53: 0.07 | N53: 0.07 | O53: 0.07 | P53: 0.07 | Q53: 0.07 | R53: 0.07 | S53: 0.07 | T53: 0.05 | U53: 0.05 | V53: 0.05 | W53: 0.05 | X53: 0.05 | Y53: 0.05 | Z53: 0.05 | AA53: 0.05 | AB53: 0.05 | AC53: 0.05 | AD53: 0.05 | AE53: 0.05 | AF53: 0.05 | AG53: 0.05 | AH53: 0.05 | AI53: 0.05 | AJ53: 0.05 | AK53: 0.05 | AL53: 0.05 | AM53: 0.05 | AN53: 0.05 | AO53: 0.05 | AP53: 0.05 | AQ53: 0.05 | AR53: 0.03 | AS53: 0.03 | AT53: 0.03 | AU53: 0.03 | AV53: 0.03 | AW53: 0.03 | AX53: 0.03 | AY53: 0.03 | AZ53: 0.03 | BA53: 0.03 | BB53: 0.03 | BC53: 0.03 | BD53: 0.02 | BE53: 0.02 | BF53: 0.02 | BG53: 0.02 | BH53: 0.02 | BI53: 0.02 | BJ53: 0.02 | BK53: 0.02 | BL53: 0.02 | BM53: 0.02 | BN53: 0.02 | BO53: 0.02 | BP53: 0.02
C54: Andrew Digital Commerce | F54: [%] | H54: 0.12 | I54: 0.12 | J54: 0.12 | K54: 0.12 | L54: 0.12 | M54: 0.12 | N54: 0.12 | O54: 0.12 | P54: 0.12 | Q54: 0.12 | R54: 0.12 | S54: 0.12 | T54: 0.06 | U54: 0.06 | V54: 0.06 | W54: 0.06 | X54: 0.06 | Y54: 0.06 | Z54: 0.06 | AA54: 0.06 | AB54: 0.06 | AC54: 0.06 | AD54: 0.06 | AE54: 0.06 | AF54: 0.02 | AG54: 0.02 | AH54: 0.02 | AI54: 0.02 | AJ54: 0.02 | AK54: 0.02 | AL54: 0.02 | AM54: 0.02 | AN54: 0.02 | AO54: 0.02 | AP54: 0.02 | AQ54: 0.02 | AR54: 0 | AS54: 0 | AT54: 0 | AU54: 0 | AV54: 0 | AW54: 0 | AX54: 0 | AY54: 0 | AZ54: 0 | BA54: 0 | BB54: 0 | BC54: 0 | BD54: 0 | BE54: 0 | BF54: 0 | BG54: 0 | BH54: 0 | BI54: 0 | BJ54: 0 | BK54: 0 | BL54: 0 | BM54: 0 | BN54: 0 | BO54: 0 | BP54: 0
C55: Anup Industrial Systems | F55: [%] | H55: 0.01 | I55: 0.01 | J55: 0.01 | K55: 0.01 | L55: 0.01 | M55: 0.01 | N55: 0.01 | O55: 0.01 | P55: 0.01 | Q55: 0.01 | R55: 0.01 | S55: 0.01 | T55: 0.005 | U55: 0.005 | V55: 0.005 | W55: 0.005 | X55: 0.005 | Y55: 0.005 | Z55: 0.005 | AA55: 0.005 | AB55: 0.005 | AC55: 0.005 | AD55: 0.005 | AE55: 0.005 | AF55: 0 | AG55: 0 | AH55: 0 | AI55: 0 | AJ55: 0 | AK55: 0 | AL55: 0 | AM55: 0 | AN55: 0 | AO55: 0 | AP55: 0 | AQ55: 0 | AR55: -0.01 | AS55: -0.01 | AT55: -0.01 | AU55: -0.01 | AV55: -0.01 | AW55: -0.01 | AX55: -0.01 | AY55: -0.01 | AZ55: -0.01 | BA55: -0.01 | BB55: -0.01 | BC55: -0.01 | BD55: -0.015 | BE55: -0.015 | BF55: -0.015 | BG55: -0.015 | BH55: -0.015 | BI55: -0.015 | BJ55: -0.015 | BK55: -0.015 | BL55: -0.015 | BM55: -0.015 | BN55: -0.015 | BO55: -0.015 | BP55: -0.015
C56: Joseph Retail Group | F56: [%] | H56: -0.08 | I56: -0.08 | J56: -0.08 | K56: -0.08 | L56: -0.08 | M56: -0.08 | N56: -0.08 | O56: -0.08 | P56: -0.08 | Q56: -0.08 | R56: -0.08 | S56: -0.08 | T56: -0.04 | U56: -0.04 | V56: -0.04 | W56: -0.04 | X56: -0.04 | Y56: -0.04 | Z56: -0.04 | AA56: -0.04 | AB56: -0.04 | AC56: -0.04 | AD56: -0.04 | AE56: -0.04 | AF56: -0.06 | AG56: -0.06 | AH56: -0.06 | AI56: -0.06 | AJ56: -0.06 | AK56: -0.06 | AL56: -0.06 | AM56: -0.06 | AN56: -0.06 | AO56: -0.06 | AP56: -0.06 | AQ56: -0.06 | AR56: -0.08 | AS56: -0.08 | AT56: -0.08 | AU56: -0.08 | AV56: -0.08 | AW56: -0.08 | AX56: -0.08 | AY56: -0.08 | AZ56: -0.08 | BA56: -0.08 | BB56: -0.08 | BC56: -0.08 | BD56: -0.07 | BE56: -0.07 | BF56: -0.07 | BG56: -0.07 | BH56: -0.07 | BI56: -0.07 | BJ56: -0.07 | BK56: -0.07 | BL56: -0.07 | BM56: -0.07 | BN56: -0.07 | BO56: -0.07 | BP56: -0.07
C57: Dim Collective | F57: [%] | H57: 0.3 | I57: 0.3 | J57: 0.3 | K57: 0.3 | L57: 0.3 | M57: 0.3 | N57: 0.3 | O57: 0.3 | P57: 0.3 | Q57: 0.3 | R57: 0.3 | S57: 0.3 | T57: 0.15 | U57: 0.15 | V57: 0.15 | W57: 0.15 | X57: 0.15 | Y57: 0.15 | Z57: 0.15 | AA57: 0.15 | AB57: 0.15 | AC57: 0.15 | AD57: 0.15 | AE57: 0.15 | AF57: 0.1 | AG57: 0.1 | AH57: 0.1 | AI57: 0.1 | AJ57: 0.1 | AK57: 0.1 | AL57: 0.1 | AM57: 0.1 | AN57: 0.1 | AO57: 0.1 | AP57: 0.1 | AQ57: 0.1 | AR57: 0.06 | AS57: 0.06 | AT57: 0.06 | AU57: 0.06 | AV57: 0.06 | AW57: 0.06 | AX57: 0.06 | AY57: 0.06 | AZ57: 0.06 | BA57: 0.06 | BB57: 0.06 | BC57: 0.06 | BD57: 0.04 | BE57: 0.04 | BF57: 0.04 | BG57: 0.04 | BH57: 0.04 | BI57: 0.04 | BJ57: 0.04 | BK57: 0.04 | BL57: 0.04 | BM57: 0.04 | BN57: 0.04 | BO57: 0.04 | BP57: 0.04
C58: Tim Forward Brands | F58: [%] | H58: 0 | I58: 0 | J58: 0 | K58: 0 | L58: 0 | M58: 0 | N58: 0 | O58: 0 | P58: 0 | Q58: 0 | R58: 0 | S58: 0 | T58: 0 | U58: 0 | V58: 0 | W58: 0 | X58: 0 | Y58: 0 | Z58: 0 | AA58: 0 | AB58: 0 | AC58: 0 | AD58: 0 | AE58: 0 | AF58: 0 | AG58: 0 | AH58: 0 | AI58: 0 | AJ58: 0 | AK58: 0 | AL58: 0 | AM58: 0 | AN58: 0 | AO58: 0 | AP58: 0 | AQ58: 0 | AR58: 0.1448 | AS58: 0.1448 | AT58: 0.1448 | AU58: 0.1448 | AV58: 0.1448 | AW58: 0.1448 | AX58: 0.1448 | AY58: 0.1448 | AZ58: 0.1448 | BA58: 0.1448 | BB58: 0.1448 | BC58: 0.1448 | BD58: 0.04 | BE58: 0.04 | BF58: 0.04 | BG58: 0.04 | BH58: 0.04 | BI58: 0.04 | BJ58: 0.04 | BK58: 0.04 | BL58: 0.04 | BM58: 0.04 | BN58: 0.04 | BO58: 0.04 | BP58: 0.04
B60: 3 Volumes
B62: Base Annual Parcels
C63: {=cust} -> Michael’s Market Goods | D63: {=starting_parc} -> 375000 | E63: ="Starting " & Assumptions!E24 -> Starting Monthly Outbound Parcels | F63: [parcel] | G63: {=starting_parc} -> 375000 | H63: {=INDEX(Assumptions!$K$36:$P$41,_xlfn.XMATCH(_xlfn.ANCHORARRAY(Model!C63),Assumptions!$B$36:$B$41),$H$10:$BP$10-$G$10)*H35:BP40} -> 401250 | I63: 401250 | J63: 401250 | K63: 401250 | L63: 401250 | M63: 401250 | N63: 401250 | O63: 401250 | P63: 401250 | Q63: 401250 | R63: 401250 | S63: 401250 | T63: 421312.5 | U63: 421312.5 | V63: 421312.5 | W63: 421312.5 | X63: 421312.5 | Y63: 421312.5 | Z63: 421312.5 | AA63: 421312.5 | AB63: 421312.5 | AC63: 421312.5 | AD63: 421312.5 | AE63: 421312.5 | AF63: 442378.12 | AG63: 442378.12 | AH63: 442378.12 | AI63: 442378.12 | AJ63: 442378.12 | AK63: 442378.12 | AL63: 442378.12 | AM63: 442378.12 | AN63: 442378.12 | AO63: 442378.12 | AP63: 442378.12 | AQ63: 442378.12 | AR63: 455649.47 | AS63: 455649.47 | AT63: 455649.47 | AU63: 455649.47 | AV63: 455649.47 | AW63: 455649.47 | AX63: 455649.47 | AY63: 455649.47 | AZ63: 455649.47 | BA63: 455649.47 | BB63: 455649.47 | BC63: 455649.47 | BD63: 464762.46 | BE63: 464762.46 | BF63: 464762.46 | BG63: 464762.46 | BH63: 464762.46 | BI63: 464762.46 | BJ63: 464762.46 | BK63: 464762.46 | BL63: 464762.46 | BM63: 464762.46 | BN63: 464762.46 | BO63: 464762.46 | BP63: 474057.71
C64: Andrew Digital Commerce | D64: 450000 | E64: ="Starting " & Assumptions!E24 -> Starting Monthly Outbound Parcels | F64: [parcel] | G64: 450000 | H64: 504000 | I64: 504000 | J64: 504000 | K64: 504000 | L64: 504000 | M64: 504000 | N64: 504000 | O64: 504000 | P64: 504000 | Q64: 504000 | R64: 504000 | S64: 504000 | T64: 534240 | U64: 534240 | V64: 534240 | W64: 534240 | X64: 534240 | Y64: 534240 | Z64: 534240 | AA64: 534240 | AB64: 534240 | AC64: 534240 | AD64: 534240 | AE64: 534240 | AF64: 544924.8 | AG64: 544924.8 | AH64: 544924.8 | AI64: 544924.8 | AJ64: 544924.8 | AK64: 544924.8 | AL64: 544924.8 | AM64: 544924.8 | AN64: 544924.8 | AO64: 544924.8 | AP64: 544924.8 | AQ64: 544924.8 | AR64: 544924.8 | AS64: 544924.8 | AT64: 544924.8 | AU64: 544924.8 | AV64: 544924.8 | AW64: 544924.8 | AX64: 544924.8 | AY64: 544924.8 | AZ64: 544924.8 | BA64: 544924.8 | BB64: 544924.8 | BC64: 544924.8 | BD64: 544924.8 | BE64: 544924.8 | BF64: 544924.8 | BG64: 544924.8 | BH64: 544924.8 | BI64: 544924.8 | BJ64: 544924.8 | BK64: 544924.8 | BL64: 544924.8 | BM64: 544924.8 | BN64: 544924.8 | BO64: 544924.8 | BP64: 544924.8
C65: Anup Industrial Systems | D65: 225000 | E65: ="Starting " & Assumptions!E24 -> Starting Monthly Outbound Parcels | F65: [parcel] | G65: 225000 | H65: 227250 | I65: 227250 | J65: 227250 | K65: 227250 | L65: 227250 | M65: 227250 | N65: 227250 | O65: 227250 | P65: 227250 | Q65: 227250 | R65: 227250 | S65: 227250 | T65: 228386.25 | U65: 228386.25 | V65: 228386.25 | W65: 228386.25 | X65: 228386.25 | Y65: 228386.25 | Z65: 228386.25 | AA65: 228386.25 | AB65: 228386.25 | AC65: 228386.25 | AD65: 228386.25 | AE65: 228386.25 | AF65: 228386.25 | AG65: 228386.25 | AH65: 228386.25 | AI65: 228386.25 | AJ65: 228386.25 | AK65: 228386.25 | AL65: 228386.25 | AM65: 228386.25 | AN65: 228386.25 | AO65: 228386.25 | AP65: 228386.25 | AQ65: 228386.25 | AR65: 226102.39 | AS65: 226102.39 | AT65: 226102.39 | AU65: 226102.39 | AV65: 226102.39 | AW65: 226102.39 | AX65: 226102.39 | AY65: 226102.39 | AZ65: 226102.39 | BA65: 226102.39 | BB65: 226102.39 | BC65: 226102.39 | BD65: 222710.85 | BE65: 222710.85 | BF65: 222710.85 | BG65: 222710.85 | BH65: 222710.85 | BI65: 222710.85 | BJ65: 222710.85 | BK65: 222710.85 | BL65: 222710.85 | BM65: 222710.85 | BN65: 222710.85 | BO65: 222710.85 | BP65: 219370.19
C66: Joseph Retail Group | D66: 300000 | E66: ="Starting " & Assumptions!E24 -> Starting Monthly Outbound Parcels | F66: [parcel] | G66: 300000 | H66: 276000 | I66: 276000 | J66: 276000 | K66: 276000 | L66: 276000 | M66: 276000 | N66: 276000 | O66: 276000 | P66: 276000 | Q66: 276000 | R66: 276000 | S66: 276000 | T66: 264960 | U66: 264960 | V66: 264960 | W66: 264960 | X66: 264960 | Y66: 264960 | Z66: 264960 | AA66: 264960 | AB66: 264960 | AC66: 264960 | AD66: 264960 | AE66: 264960 | AF66: 249062.4 | AG66: 249062.4 | AH66: 249062.4 | AI66: 249062.4 | AJ66: 249062.4 | AK66: 249062.4 | AL66: 249062.4 | AM66: 249062.4 | AN66: 249062.4 | AO66: 249062.4 | AP66: 249062.4 | AQ66: 249062.4 | AR66: 229137.41 | AS66: 229137.41 | AT66: 229137.41 | AU66: 229137.41 | AV66: 229137.41 | AW66: 229137.41 | AX66: 229137.41 | AY66: 229137.41 | AZ66: 229137.41 | BA66: 229137.41 | BB66: 229137.41 | BC66: 229137.41 | BD66: 213097.79 | BE66: 213097.79 | BF66: 213097.79 | BG66: 213097.79 | BH66: 213097.79 | BI66: 213097.79 | BJ66: 213097.79 | BK66: 213097.79 | BL66: 213097.79 | BM66: 213097.79 | BN66: 213097.79 | BO66: 213097.79 | BP66: 198180.94
C67: Dim Collective | D67: 125000 | E67: ="Starting " & Assumptions!E24 -> Starting Monthly Outbound Parcels | F67: [parcel] | G67: 125000 | H67: 162500 | I67: 162500 | J67: 162500 | K67: 162500 | L67: 162500 | M67: 162500 | N67: 162500 | O67: 162500 | P67: 162500 | Q67: 162500 | R67: 162500 | S67: 162500 | T67: 186875 | U67: 186875 | V67: 186875 | W67: 186875 | X67: 186875 | Y67: 186875 | Z67: 186875 | AA67: 186875 | AB67: 186875 | AC67: 186875 | AD67: 186875 | AE67: 186875 | AF67: 205562.5 | AG67: 205562.5 | AH67: 205562.5 | AI67: 205562.5 | AJ67: 205562.5 | AK67: 205562.5 | AL67: 205562.5 | AM67: 205562.5 | AN67: 205562.5 | AO67: 205562.5 | AP67: 205562.5 | AQ67: 205562.5 | AR67: 217896.25 | AS67: 217896.25 | AT67: 217896.25 | AU67: 217896.25 | AV67: 217896.25 | AW67: 217896.25 | AX67: 217896.25 | AY67: 217896.25 | AZ67: 217896.25 | BA67: 217896.25 | BB67: 217896.25 | BC67: 217896.25 | BD67: 226612.1 | BE67: 226612.1 | BF67: 226612.1 | BG67: 226612.1 | BH67: 226612.1 | BI67: 226612.1 | BJ67: 226612.1 | BK67: 226612.1 | BL67: 226612.1 | BM67: 226612.1 | BN67: 226612.1 | BO67: 226612.1 | BP67: 235676.58
C68: Tim Forward Brands | D68: 250000 | E68: ="Starting " & Assumptions!E24 -> Starting Monthly Outbound Parcels | F68: [parcel] | G68: 250000 | H68: 0 | I68: 0 | J68: 0 | K68: 0 | L68: 0 | M68: 0 | N68: 0 | O68: 0 | P68: 0 | Q68: 0 | R68: 0 | S68: 0 | T68: 0 | U68: 0 | V68: 0 | W68: 0 | X68: 0 | Y68: 0 | Z68: 0 | AA68: 0 | AB68: 0 | AC68: 0 | AD68: 0 | AE68: 0 | AF68: 0 | AG68: 0 | AH68: 0 | AI68: 0 | AJ68: 0 | AK68: 0 | AL68: 0 | AM68: 0 | AN68: 0 | AO68: 0 | AP68: 0 | AQ68: 0 | AR68: 0 | AS68: 0 | AT68: 0 | AU68: 0 | AV68: 0 | AW68: 0 | AX68: 0 | AY68: 0 | AZ68: 0 | BA68: 0 | BB68: 0 | BC68: 0 | BD68: 0 | BE68: 0 | BF68: 0 | BG68: 0 | BH68: 0 | BI68: 0 | BJ68: 0 | BK68: 0 | BL68: 0 | BM68: 0 | BN68: 0 | BO68: 0 | BP68: 0
B70: Outbound Parcel with Demand
C71: {=cust} -> Michael’s Market Goods | F71: [parcel] | G71: {=_xlfn.ANCHORARRAY(G63)*G35:G40} -> 0 | H71: {=H63:BP68*H45:BP50*H35:BP40} -> 300937.5 | I71: 321000 | J71: 341062.5 | K71: 381187.5 | L71: 441375 | M71: 481500 | N71: 361125 | O71: 341062.5 | P71: 401250 | Q71: 421312.5 | R71: 481500 | S71: 541687.5 | T71: 315984.38 | U71: 337050 | V71: 358115.62 | W71: 400246.88 | X71: 463443.75 | Y71: 505575 | Z71: 379181.25 | AA71: 358115.62 | AB71: 421312.5 | AC71: 442378.12 | AD71: 505575 | AE71: 568771.88 | AF71: 331783.59 | AG71: 353902.5 | AH71: 376021.41 | AI71: 420259.22 | AJ71: 486615.94 | AK71: 530853.75 | AL71: 398140.31 | AM71: 376021.41 | AN71: 442378.12 | AO71: 464497.03 | AP71: 530853.75 | AQ71: 597210.47 | AR71: 341737.1 | AS71: 364519.58 | AT71: 387302.05 | AU71: 432867 | AV71: 501214.42 | AW71: 546779.36 | AX71: 410084.52 | AY71: 387302.05 | AZ71: 455649.47 | BA71: 478431.94 | BB71: 546779.36 | BC71: 615126.78 | BD71: 348571.84 | BE71: 371809.97 | BF71: 395048.09 | BG71: 441524.34 | BH71: 511238.7 | BI71: 557714.95 | BJ71: 418286.21 | BK71: 395048.09 | BL71: 464762.46 | BM71: 488000.58 | BN71: 557714.95 | BO71: 627429.32 | BP71: 355543.28
C72: Andrew Digital Commerce | F72: [parcel] | G72: 0 | H72: 378000 | I72: 327600 | J72: 352800 | K72: 378000 | L72: 352800 | M72: 378000 | N72: 352800 | O72: 453600 | P72: 529200 | Q72: 554400 | R72: 882000 | S72: 1108800 | T72: 400680 | U72: 347256 | V72: 373968 | W72: 400680 | X72: 373968 | Y72: 400680 | Z72: 373968 | AA72: 480816 | AB72: 560952 | AC72: 587664 | AD72: 934920 | AE72: 1175328 | AF72: 408693.6 | AG72: 354201.12 | AH72: 381447.36 | AI72: 408693.6 | AJ72: 381447.36 | AK72: 408693.6 | AL72: 381447.36 | AM72: 490432.32 | AN72: 572171.04 | AO72: 599417.28 | AP72: 953618.4 | AQ72: 1198834.6 | AR72: 408693.6 | AS72: 354201.12 | AT72: 381447.36 | AU72: 408693.6 | AV72: 381447.36 | AW72: 408693.6 | AX72: 381447.36 | AY72: 490432.32 | AZ72: 572171.04 | BA72: 599417.28 | BB72: 953618.4 | BC72: 1198834.6 | BD72: 408693.6 | BE72: 354201.12 | BF72: 381447.36 | BG72: 408693.6 | BH72: 381447.36 | BI72: 408693.6 | BJ72: 381447.36 | BK72: 490432.32 | BL72: 572171.04 | BM72: 599417.28 | BN72: 953618.4 | BO72: 1198834.6 | BP72: 408693.6
C73: Anup Industrial Systems | F73: [parcel] | G73: 0 | H73: 215887.5 | I73: 215887.5 | J73: 227250 | K73: 227250 | L73: 227250 | M73: 227250 | N73: 215887.5 | O73: 204525 | P73: 249975 | Q73: 249975 | R73: 238612.5 | S73: 227250 | T73: 216966.94 | U73: 216966.94 | V73: 228386.25 | W73: 228386.25 | X73: 228386.25 | Y73: 228386.25 | Z73: 216966.94 | AA73: 205547.62 | AB73: 251224.88 | AC73: 251224.88 | AD73: 239805.56 | AE73: 228386.25 | AF73: 216966.94 | AG73: 216966.94 | AH73: 228386.25 | AI73: 228386.25 | AJ73: 228386.25 | AK73: 228386.25 | AL73: 216966.94 | AM73: 205547.62 | AN73: 251224.88 | AO73: 251224.88 | AP73: 239805.56 | AQ73: 228386.25 | AR73: 214797.27 | AS73: 214797.27 | AT73: 226102.39 | AU73: 226102.39 | AV73: 226102.39 | AW73: 226102.39 | AX73: 214797.27 | AY73: 203492.15 | AZ73: 248712.63 | BA73: 248712.63 | BB73: 237407.51 | BC73: 226102.39 | BD73: 211575.31 | BE73: 211575.31 | BF73: 222710.85 | BG73: 222710.85 | BH73: 222710.85 | BI73: 222710.85 | BJ73: 211575.31 | BK73: 200439.77 | BL73: 244981.94 | BM73: 244981.94 | BN73: 233846.39 | BO73: 222710.85 | BP73: 208401.68
C74: Joseph Retail Group | F74: [parcel] | G74: 0 | H74: 207000 | I74: 220800 | J74: 234600 | K74: 262200 | L74: 303600 | M74: 331200 | N74: 248400 | O74: 234600 | P74: 276000 | Q74: 289800 | R74: 331200 | S74: 372600 | T74: 198720 | U74: 211968 | V74: 225216 | W74: 251712 | X74: 291456 | Y74: 317952 | Z74: 238464 | AA74: 225216 | AB74: 264960 | AC74: 278208 | AD74: 317952 | AE74: 357696 | AF74: 186796.8 | AG74: 199249.92 | AH74: 211703.04 | AI74: 236609.28 | AJ74: 273968.64 | AK74: 298874.88 | AL74: 224156.16 | AM74: 211703.04 | AN74: 249062.4 | AO74: 261515.52 | AP74: 298874.88 | AQ74: 336234.24 | AR74: 171853.06 | AS74: 183309.93 | AT74: 194766.8 | AU74: 217680.54 | AV74: 252051.15 | AW74: 274964.89 | AX74: 206223.67 | AY74: 194766.8 | AZ74: 229137.41 | BA74: 240594.28 | BB74: 274964.89 | BC74: 309335.5 | BD74: 159823.34 | BE74: 170478.23 | BF74: 181133.12 | BG74: 202442.9 | BH74: 234407.57 | BI74: 255717.35 | BJ74: 191788.01 | BK74: 181133.12 | BL74: 213097.79 | BM74: 223752.68 | BN74: 255717.35 | BO74: 287682.02 | BP74: 148635.71
C75: Dim Collective | F75: [parcel] | G75: 0 | H75: 121875 | I75: 130000 | J75: 138125 | K75: 154375 | L75: 178750 | M75: 195000 | N75: 146250 | O75: 138125 | P75: 162500 | Q75: 170625 | R75: 195000 | S75: 219375 | T75: 140156.25 | U75: 149500 | V75: 158843.75 | W75: 177531.25 | X75: 205562.5 | Y75: 224250 | Z75: 168187.5 | AA75: 158843.75 | AB75: 186875 | AC75: 196218.75 | AD75: 224250 | AE75: 252281.25 | AF75: 154171.88 | AG75: 164450 | AH75: 174728.13 | AI75: 195284.38 | AJ75: 226118.75 | AK75: 246675 | AL75: 185006.25 | AM75: 174728.13 | AN75: 205562.5 | AO75: 215840.63 | AP75: 246675 | AQ75: 277509.38 | AR75: 163422.19 | AS75: 174317 | AT75: 185211.81 | AU75: 207001.44 | AV75: 239685.88 | AW75: 261475.5 | AX75: 196106.63 | AY75: 185211.81 | AZ75: 217896.25 | BA75: 228791.06 | BB75: 261475.5 | BC75: 294159.94 | BD75: 169959.08 | BE75: 181289.68 | BF75: 192620.29 | BG75: 215281.5 | BH75: 249273.31 | BI75: 271934.52 | BJ75: 203950.89 | BK75: 192620.29 | BL75: 226612.1 | BM75: 237942.71 | BN75: 271934.52 | BO75: 305926.34 | BP75: 176757.44
C76: Tim Forward Brands | F76: [parcel] | G76: 0 | H76: 0 | I76: 0 | J76: 0 | K76: 0 | L76: 0 | M76: 0 | N76: 0 | O76: 0 | P76: 0 | Q76: 0 | R76: 0 | S76: 0 | T76: 0 | U76: 0 | V76: 0 | W76: 0 | X76: 0 | Y76: 0 | Z76: 0 | AA76: 0 | AB76: 0 | AC76: 0 | AD76: 0 | AE76: 0 | AF76: 0 | AG76: 0 | AH76: 0 | AI76: 0 | AJ76: 0 | AK76: 0 | AL76: 0 | AM76: 0 | AN76: 0 | AO76: 0 | AP76: 0 | AQ76: 0 | AR76: 0 | AS76: 0 | AT76: 0 | AU76: 0 | AV76: 0 | AW76: 0 | AX76: 0 | AY76: 0 | AZ76: 0 | BA76: 0 | BB76: 0 | BC76: 0 | BD76: 0 | BE76: 0 | BF76: 0 | BG76: 0 | BH76: 0 | BI76: 0 | BJ76: 0 | BK76: 0 | BL76: 0 | BM76: 0 | BN76: 0 | BO76: 0 | BP76: 0
C77: Total Outbound Parcels | F77: [parcel] | G77: =SUM(_xlfn.ANCHORARRAY(G71)) -> 0 | H77: =SUM(H71:H76) -> 1223700 | I77: =SUM(I71:I76) -> 1215287.5 | J77: =SUM(J71:J76) -> 1293837.5 | K77: =SUM(K71:K76) -> 1403012.5 | L77: =SUM(L71:L76) -> 1503775 | M77: =SUM(M71:M76) -> 1612950 | N77: =SUM(N71:N76) -> 1324462.5 | O77: =SUM(O71:O76) -> 1371912.5 | ... BP77: =SUM(BP71:BP76) -> 1298031.7
B79: Outbound Pallets with Demand
C80: {=cust} -> Michael’s Market Goods | D80: {=PPP} -> 18 | E80: pallets/parcel | F80: [pallet] | G80: {=_xlfn.ANCHORARRAY(G63)*G35:G40} -> 0 | H80: {=H71:BP76/_xlfn.ANCHORARRAY(D80)} -> 16718.75 | I80: 17833.333 | J80: 18947.917 | K80: 21177.083 | L80: 24520.833 | M80: 26750 | N80: 20062.5 | O80: 18947.917 | P80: 22291.667 | Q80: 23406.25 | R80: 26750 | S80: 30093.75 | T80: 17554.688 | U80: 18725 | V80: 19895.312 | W80: 22235.938 | X80: 25746.875 | Y80: 28087.5 | Z80: 21065.625 | AA80: 19895.312 | AB80: 23406.25 | AC80: 24576.562 | AD80: 28087.5 | AE80: 31598.438 | AF80: 18432.422 | AG80: 19661.25 | AH80: 20890.078 | AI80: 23347.734 | AJ80: 27034.219 | AK80: 29491.875 | AL80: 22118.906 | AM80: 20890.078 | AN80: 24576.562 | AO80: 25805.391 | AP80: 29491.875 | AQ80: 33178.359 | AR80: 18985.395 | AS80: 20251.088 | AT80: 21516.78 | AU80: 24048.166 | AV80: 27845.245 | AW80: 30376.631 | AX80: 22782.473 | AY80: 21516.78 | AZ80: 25313.859 | BA80: 26579.552 | BB80: 30376.631 | BC80: 34173.71 | BD80: 19365.102 | BE80: 20656.109 | BF80: 21947.116 | BG80: 24529.13 | BH80: 28402.15 | BI80: 30984.164 | BJ80: 23238.123 | BK80: 21947.116 | BL80: 25820.137 | BM80: 27111.143 | BN80: 30984.164 | BO80: 34857.184 | BP80: 19752.404
C81: Andrew Digital Commerce | D81: 30 | E81: pallets/parcel | F81: [pallet] | G81: 0 | H81: 12600 | I81: 10920 | J81: 11760 | K81: 12600 | L81: 11760 | M81: 12600 | N81: 11760 | O81: 15120 | P81: 17640 | Q81: 18480 | R81: 29400 | S81: 36960 | T81: 13356 | U81: 11575.2 | V81: 12465.6 | W81: 13356 | X81: 12465.6 | Y81: 13356 | Z81: 12465.6 | AA81: 16027.2 | AB81: 18698.4 | AC81: 19588.8 | AD81: 31164 | AE81: 39177.6 | AF81: 13623.12 | AG81: 11806.704 | AH81: 12714.912 | AI81: 13623.12 | AJ81: 12714.912 | AK81: 13623.12 | AL81: 12714.912 | AM81: 16347.744 | AN81: 19072.368 | AO81: 19980.576 | AP81: 31787.28 | AQ81: 39961.152 | AR81: 13623.12 | AS81: 11806.704 | AT81: 12714.912 | AU81: 13623.12 | AV81: 12714.912 | AW81: 13623.12 | AX81: 12714.912 | AY81: 16347.744 | AZ81: 19072.368 | BA81: 19980.576 | BB81: 31787.28 | BC81: 39961.152 | BD81: 13623.12 | BE81: 11806.704 | BF81: 12714.912 | BG81: 13623.12 | BH81: 12714.912 | BI81: 13623.12 | BJ81: 12714.912 | BK81: 16347.744 | BL81: 19072.368 | BM81: 19980.576 | BN81: 31787.28 | BO81: 39961.152 | BP81: 13623.12
C82: Anup Industrial Systems | D82: 15 | E82: pallets/parcel | F82: [pallet] | G82: 0 | H82: 14392.5 | I82: 14392.5 | J82: 15150 | K82: 15150 | L82: 15150 | M82: 15150 | N82: 14392.5 | O82: 13635 | P82: 16665 | Q82: 16665 | R82: 15907.5 | S82: 15150 | T82: 14464.462 | U82: 14464.462 | V82: 15225.75 | W82: 15225.75 | X82: 15225.75 | Y82: 15225.75 | Z82: 14464.462 | AA82: 13703.175 | AB82: 16748.325 | AC82: 16748.325 | AD82: 15987.037 | AE82: 15225.75 | AF82: 14464.462 | AG82: 14464.462 | AH82: 15225.75 | AI82: 15225.75 | AJ82: 15225.75 | AK82: 15225.75 | AL82: 14464.462 | AM82: 13703.175 | AN82: 16748.325 | AO82: 16748.325 | AP82: 15987.037 | AQ82: 15225.75 | AR82: 14319.818 | AS82: 14319.818 | AT82: 15073.492 | AU82: 15073.492 | AV82: 15073.492 | AW82: 15073.492 | AX82: 14319.818 | AY82: 13566.143 | AZ82: 16580.842 | BA82: 16580.842 | BB82: 15827.167 | BC82: 15073.492 | BD82: 14105.021 | BE82: 14105.021 | BF82: 14847.39 | BG82: 14847.39 | BH82: 14847.39 | BI82: 14847.39 | BJ82: 14105.021 | BK82: 13362.651 | BL82: 16332.129 | BM82: 16332.129 | BN82: 15589.76 | BO82: 14847.39 | BP82: 13893.445
C83: Joseph Retail Group | D83: 22 | E83: pallets/parcel | F83: [pallet] | G83: 0 | H83: 9409.0909 | I83: 10036.364 | J83: 10663.636 | K83: 11918.182 | L83: 13800 | M83: 15054.545 | N83: 11290.909 | O83: 10663.636 | P83: 12545.455 | Q83: 13172.727 | R83: 15054.545 | S83: 16936.364 | T83: 9032.7273 | U83: 9634.9091 | V83: 10237.091 | W83: 11441.455 | X83: 13248 | Y83: 14452.364 | Z83: 10839.273 | AA83: 10237.091 | AB83: 12043.636 | AC83: 12645.818 | AD83: 14452.364 | AE83: 16258.909 | AF83: 8490.7636 | AG83: 9056.8145 | AH83: 9622.8655 | AI83: 10754.967 | AJ83: 12453.12 | AK83: 13585.222 | AL83: 10188.916 | AM83: 9622.8655 | AN83: 11321.018 | AO83: 11887.069 | AP83: 13585.222 | AQ83: 15283.375 | AR83: 7811.5025 | AS83: 8332.2694 | AT83: 8853.0362 | AU83: 9894.5699 | AV83: 11456.87 | AW83: 12498.404 | AX83: 9373.8031 | AY83: 8853.0362 | AZ83: 10415.337 | BA83: 10936.104 | BB83: 12498.404 | BC83: 14060.705 | BD83: 7264.6974 | BE83: 7749.0105 | BF83: 8233.3237 | BG83: 9201.95 | BH83: 10654.889 | BI83: 11623.516 | BJ83: 8717.6368 | BK83: 8233.3237 | BL83: 9686.2632 | BM83: 10170.576 | BN83: 11623.516 | BO83: 13076.455 | BP83: 6756.1686
C84: Dim Collective | D84: 25 | E84: pallets/parcel | F84: [pallet] | G84: 0 | H84: 4875 | I84: 5200 | J84: 5525 | K84: 6175 | L84: 7150 | M84: 7800 | N84: 5850 | O84: 5525 | P84: 6500 | Q84: 6825 | R84: 7800 | S84: 8775 | T84: 5606.25 | U84: 5980 | V84: 6353.75 | W84: 7101.25 | X84: 8222.5 | Y84: 8970 | Z84: 6727.5 | AA84: 6353.75 | AB84: 7475 | AC84: 7848.75 | AD84: 8970 | AE84: 10091.25 | AF84: 6166.875 | AG84: 6578 | AH84: 6989.125 | AI84: 7811.375 | AJ84: 9044.75 | AK84: 9867 | AL84: 7400.25 | AM84: 6989.125 | AN84: 8222.5 | AO84: 8633.625 | AP84: 9867 | AQ84: 11100.375 | AR84: 6536.8875 | AS84: 6972.68 | AT84: 7408.4725 | AU84: 8280.0575 | AV84: 9587.435 | AW84: 10459.02 | AX84: 7844.265 | AY84: 7408.4725 | AZ84: 8715.85 | BA84: 9151.6425 | BB84: 10459.02 | BC84: 11766.398 | BD84: 6798.363 | BE84: 7251.5872 | BF84: 7704.8114 | BG84: 8611.2598 | BH84: 9970.9324 | BI84: 10877.381 | BJ84: 8158.0356 | BK84: 7704.8114 | BL84: 9064.484 | BM84: 9517.7082 | BN84: 10877.381 | BO84: 12237.053 | BP84: 7070.2975
C85: Tim Forward Brands | D85: 15 | E85: pallets/parcel | F85: [pallet] | G85: 0 | H85: 0 | I85: 0 | J85: 0 | K85: 0 | L85: 0 | M85: 0 | N85: 0 | O85: 0 | P85: 0 | Q85: 0 | R85: 0 | S85: 0 | T85: 0 | U85: 0 | V85: 0 | W85: 0 | X85: 0 | Y85: 0 | Z85: 0 | AA85: 0 | AB85: 0 | AC85: 0 | AD85: 0 | AE85: 0 | AF85: 0 | AG85: 0 | AH85: 0 | AI85: 0 | AJ85: 0 | AK85: 0 | AL85: 0 | AM85: 0 | AN85: 0 | AO85: 0 | AP85: 0 | AQ85: 0 | AR85: 0 | AS85: 0 | AT85: 0 | AU85: 0 | AV85: 0 | AW85: 0 | AX85: 0 | AY85: 0 | AZ85: 0 | BA85: 0 | BB85: 0 | BC85: 0 | BD85: 0 | BE85: 0 | BF85: 0 | BG85: 0 | BH85: 0 | BI85: 0 | BJ85: 0 | BK85: 0 | BL85: 0 | BM85: 0 | BN85: 0 | BO85: 0 | BP85: 0
C86: Total Outbound Pallets | F86: [parcel] | G86: =SUM(_xlfn.ANCHORARRAY(G80)) -> 0 | H86: =SUM(H80:H85) -> 57995.341 | I86: =SUM(I80:I85) -> 58382.197 | J86: =SUM(J80:J85) -> 62046.553 | K86: =SUM(K80:K85) -> 67020.265 | L86: =SUM(L80:L85) -> 72380.833 | M86: =SUM(M80:M85) -> 77354.545 | N86: =SUM(N80:N85) -> 63355.909 | O86: =SUM(O80:O85) -> 63891.553 | ... BP86: =SUM(BP80:BP85) -> 61095.436
B88: Inbound Pallets with Demand
C89: {=cust} -> Michael’s Market Goods | D89: {=ib_rate} -> 0.03 | E89: =Assumptions!H24 -> Assortment Growth Rate | F89: [pallet] | G89: {=G63*G35:G40} -> 0 | H89: {=I80:BP85*(1+_xlfn.ANCHORARRAY(D89))} -> 18368.333 | I89: 19516.354 | J89: 21812.396 | K89: 25256.458 | L89: 27552.5 | M89: 20664.375 | N89: 19516.354 | O89: 22960.417 | P89: 24108.438 | Q89: 27552.5 | R89: 30996.562 | S89: 18081.328 | T89: 19286.75 | U89: 20492.172 | V89: 22903.016 | W89: 26519.281 | X89: 28930.125 | Y89: 21697.594 | Z89: 20492.172 | AA89: 24108.438 | AB89: 25313.859 | AC89: 28930.125 | AD89: 32546.391 | AE89: 18985.395 | AF89: 20251.088 | AG89: 21516.78 | AH89: 24048.166 | AI89: 27845.245 | AJ89: 30376.631 | AK89: 22782.473 | AL89: 21516.78 | AM89: 25313.859 | AN89: 26579.552 | AO89: 30376.631 | AP89: 34173.71 | AQ89: 19554.956 | AR89: 20858.62 | AS89: 22162.284 | AT89: 24769.611 | AU89: 28680.603 | AV89: 31287.93 | AW89: 23465.948 | AX89: 22162.284 | AY89: 26073.275 | AZ89: 27376.939 | BA89: 31287.93 | BB89: 35198.921 | BC89: 19946.055 | BD89: 21275.793 | BE89: 22605.53 | BF89: 25265.004 | BG89: 29254.215 | BH89: 31913.689 | BI89: 23935.267 | BJ89: 22605.53 | BK89: 26594.741 | BL89: 27924.478 | BM89: 31913.689 | BN89: 35902.9 | BO89: 20344.977
C90: Andrew Digital Commerce | D90: 0.06 | E90: =Assumptions!H24 -> Assortment Growth Rate | F90: [pallet] | G90: 0 | H90: 11575.2 | I90: 12465.6 | J90: 13356 | K90: 12465.6 | L90: 13356 | M90: 12465.6 | N90: 16027.2 | O90: 18698.4 | P90: 19588.8 | Q90: 31164 | R90: 39177.6 | S90: 14157.36 | T90: 12269.712 | U90: 13213.536 | V90: 14157.36 | W90: 13213.536 | X90: 14157.36 | Y90: 13213.536 | Z90: 16988.832 | AA90: 19820.304 | AB90: 20764.128 | AC90: 33033.84 | AD90: 41528.256 | AE90: 14440.507 | AF90: 12515.106 | AG90: 13477.807 | AH90: 14440.507 | AI90: 13477.807 | AJ90: 14440.507 | AK90: 13477.807 | AL90: 17328.609 | AM90: 20216.71 | AN90: 21179.411 | AO90: 33694.517 | AP90: 42358.821 | AQ90: 14440.507 | AR90: 12515.106 | AS90: 13477.807 | AT90: 14440.507 | AU90: 13477.807 | AV90: 14440.507 | AW90: 13477.807 | AX90: 17328.609 | AY90: 20216.71 | AZ90: 21179.411 | BA90: 33694.517 | BB90: 42358.821 | BC90: 14440.507 | BD90: 12515.106 | BE90: 13477.807 | BF90: 14440.507 | BG90: 13477.807 | BH90: 14440.507 | BI90: 13477.807 | BJ90: 17328.609 | BK90: 20216.71 | BL90: 21179.411 | BM90: 33694.517 | BN90: 42358.821 | BO90: 14440.507
C91: Anup Industrial Systems | D91: 0.01 | E91: =Assumptions!H24 -> Assortment Growth Rate | F91: [pallet] | G91: 0 | H91: 14536.425 | I91: 15301.5 | J91: 15301.5 | K91: 15301.5 | L91: 15301.5 | M91: 14536.425 | N91: 13771.35 | O91: 16831.65 | P91: 16831.65 | Q91: 16066.575 | R91: 15301.5 | S91: 14609.107 | T91: 14609.107 | U91: 15378.007 | V91: 15378.007 | W91: 15378.007 | X91: 15378.007 | Y91: 14609.107 | Z91: 13840.207 | AA91: 16915.808 | AB91: 16915.808 | AC91: 16146.908 | AD91: 15378.007 | AE91: 14609.107 | AF91: 14609.107 | AG91: 15378.007 | AH91: 15378.007 | AI91: 15378.007 | AJ91: 15378.007 | AK91: 14609.107 | AL91: 13840.207 | AM91: 16915.808 | AN91: 16915.808 | AO91: 16146.908 | AP91: 15378.007 | AQ91: 14463.016 | AR91: 14463.016 | AS91: 15224.227 | AT91: 15224.227 | AU91: 15224.227 | AV91: 15224.227 | AW91: 14463.016 | AX91: 13701.805 | AY91: 16746.65 | AZ91: 16746.65 | BA91: 15985.439 | BB91: 15224.227 | BC91: 14246.071 | BD91: 14246.071 | BE91: 14995.864 | BF91: 14995.864 | BG91: 14995.864 | BH91: 14995.864 | BI91: 14246.071 | BJ91: 13496.278 | BK91: 16495.45 | BL91: 16495.45 | BM91: 15745.657 | BN91: 14995.864 | BO91: 14032.38
C92: Joseph Retail Group | D92: 0 | E92: =Assumptions!H24 -> Assortment Growth Rate | F92: [pallet] | G92: 0 | H92: 10036.364 | I92: 10663.636 | J92: 11918.182 | K92: 13800 | L92: 15054.545 | M92: 11290.909 | N92: 10663.636 | O92: 12545.455 | P92: 13172.727 | Q92: 15054.545 | R92: 16936.364 | S92: 9032.7273 | T92: 9634.9091 | U92: 10237.091 | V92: 11441.455 | W92: 13248 | X92: 14452.364 | Y92: 10839.273 | Z92: 10237.091 | AA92: 12043.636 | AB92: 12645.818 | AC92: 14452.364 | AD92: 16258.909 | AE92: 8490.7636 | AF92: 9056.8145 | AG92: 9622.8655 | AH92: 10754.967 | AI92: 12453.12 | AJ92: 13585.222 | AK92: 10188.916 | AL92: 9622.8655 | AM92: 11321.018 | AN92: 11887.069 | AO92: 13585.222 | AP92: 15283.375 | AQ92: 7811.5025 | AR92: 8332.2694 | AS92: 8853.0362 | AT92: 9894.5699 | AU92: 11456.87 | AV92: 12498.404 | AW92: 9373.8031 | AX92: 8853.0362 | AY92: 10415.337 | AZ92: 10936.104 | BA92: 12498.404 | BB92: 14060.705 | BC92: 7264.6974 | BD92: 7749.0105 | BE92: 8233.3237 | BF92: 9201.95 | BG92: 10654.889 | BH92: 11623.516 | BI92: 8717.6368 | BJ92: 8233.3237 | BK92: 9686.2632 | BL92: 10170.576 | BM92: 11623.516 | BN92: 13076.455 | BO92: 6756.1686
C93: Dim Collective | D93: 0.08 | E93: =Assumptions!H24 -> Assortment Growth Rate | F93: [pallet] | G93: 0 | H93: 5616 | I93: 5967 | J93: 6669 | K93: 7722 | L93: 8424 | M93: 6318 | N93: 5967 | O93: 7020 | P93: 7371 | Q93: 8424 | R93: 9477 | S93: 6054.75 | T93: 6458.4 | U93: 6862.05 | V93: 7669.35 | W93: 8880.3 | X93: 9687.6 | Y93: 7265.7 | Z93: 6862.05 | AA93: 8073 | AB93: 8476.65 | AC93: 9687.6 | AD93: 10898.55 | AE93: 6660.225 | AF93: 7104.24 | AG93: 7548.255 | AH93: 8436.285 | AI93: 9768.33 | AJ93: 10656.36 | AK93: 7992.27 | AL93: 7548.255 | AM93: 8880.3 | AN93: 9324.315 | AO93: 10656.36 | AP93: 11988.405 | AQ93: 7059.8385 | AR93: 7530.4944 | AS93: 8001.1503 | AT93: 8942.4621 | AU93: 10354.43 | AV93: 11295.742 | AW93: 8471.8062 | AX93: 8001.1503 | AY93: 9413.118 | AZ93: 9883.7739 | BA93: 11295.742 | BB93: 12707.709 | BC93: 7342.232 | BD93: 7831.7142 | BE93: 8321.1963 | BF93: 9300.1606 | BG93: 10768.607 | BH93: 11747.571 | BI93: 8810.6784 | BJ93: 8321.1963 | BK93: 9789.6427 | BL93: 10279.125 | BM93: 11747.571 | BN93: 13216.018 | BO93: 7635.9213
C94: Tim Forward Brands | D94: 0.09 | E94: =Assumptions!H24 -> Assortment Growth Rate | F94: [pallet] | G94: 0 | H94: 0 | I94: 0 | J94: 0 | K94: 0 | L94: 0 | M94: 0 | N94: 0 | O94: 0 | P94: 0 | Q94: 0 | R94: 0 | S94: 0 | T94: 0 | U94: 0 | V94: 0 | W94: 0 | X94: 0 | Y94: 0 | Z94: 0 | AA94: 0 | AB94: 0 | AC94: 0 | AD94: 0 | AE94: 0 | AF94: 0 | AG94: 0 | AH94: 0 | AI94: 0 | AJ94: 0 | AK94: 0 | AL94: 0 | AM94: 0 | AN94: 0 | AO94: 0 | AP94: 0 | AQ94: 0 | AR94: 0 | AS94: 0 | AT94: 0 | AU94: 0 | AV94: 0 | AW94: 0 | AX94: 0 | AY94: 0 | AZ94: 0 | BA94: 0 | BB94: 0 | BC94: 0 | BD94: 0 | BE94: 0 | BF94: 0 | BG94: 0 | BH94: 0 | BI94: 0 | BJ94: 0 | BK94: 0 | BL94: 0 | BM94: 0 | BN94: 0 | BO94: 0
C95: Total Inbound Pallest | F95: [parcel] | G95: =SUM(_xlfn.ANCHORARRAY(G89)) -> 0 | H95: =SUM(H89:H94) -> 60132.322 | I95: =SUM(I89:I94) -> 63914.091 | J95: =SUM(J89:J94) -> 69057.078 | K95: =SUM(K89:K94) -> 74545.558 | L95: =SUM(L89:L94) -> 79688.545 | M95: =SUM(M89:M94) -> 65275.309 | N95: =SUM(N89:N94) -> 65945.541 | O95: =SUM(O89:O94) -> 78055.921 | ... BP95: =SUM(BP89:BP94) -> 0
B97: Stored Pallets
C98: {=cust} -> Michael’s Market Goods | D98: {=inpal} -> 2400 | E98: =Assumptions!G24 -> Initial Balance (Pallets) | F98: [pallet] | G98: {=_xlfn.ANCHORARRAY(D98)} -> 2400 | H98: =IF(H35=0, IF(I35=H35,0,$D98), G98+H89-H80) -> 4049.5833 | I98: =IF(I35=0, IF(J35=I35,0,$D98), H98+I89-I80) -> 5732.6042 | J98: =IF(J35=0, IF(K35=J35,0,$D98), I98+J89-J80) -> 8597.0833 | K98: =IF(K35=0, IF(L35=K35,0,$D98), J98+K89-K80) -> 12676.458 | L98: =IF(L35=0, IF(M35=L35,0,$D98), K98+L89-L80) -> 15708.125 | M98: =IF(M35=0, IF(N35=M35,0,$D98), L98+M89-M80) -> 9622.5 | N98: =IF(N35=0, IF(O35=N35,0,$D98), M98+N89-N80) -> 9076.3542 | O98: =IF(O35=0, IF(P35=O35,0,$D98), N98+O89-O80) -> 13088.854 | ... BO98: =IF(BO35=0, IF(BP35=BO35,0,$D98), BN98+BO89-BO80) -> 49231.715
C99: Andrew Digital Commerce | D99: 2100 | E99: =Assumptions!G24 -> Initial Balance (Pallets) | F99: [pallet] | G99: 2100 | H99: =IF(H36=0, IF(I36=H36,0,$D99), G99+H90-H81) -> 1075.2 | I99: =IF(I36=0, IF(J36=I36,0,$D99), H99+I90-I81) -> 2620.8 | J99: =IF(J36=0, IF(K36=J36,0,$D99), I99+J90-J81) -> 4216.8 | K99: =IF(K36=0, IF(L36=K36,0,$D99), J99+K90-K81) -> 4082.4 | L99: =IF(L36=0, IF(M36=L36,0,$D99), K99+L90-L81) -> 5678.4 | M99: =IF(M36=0, IF(N36=M36,0,$D99), L99+M90-M81) -> 5544 | N99: =IF(N36=0, IF(O36=N36,0,$D99), M99+N90-N81) -> 9811.2 | O99: =IF(O36=0, IF(P36=O36,0,$D99), N99+O90-O81) -> 13389.6 | ... BO99: =IF(BO36=0, IF(BP36=BO36,0,$D99), BN99+BO90-BO81) -> 67336.853
C100: Anup Industrial Systems | D100: 1800 | E100: =Assumptions!G24 -> Initial Balance (Pallets) | F100: [pallet] | G100: 1800 | H100: =IF(H37=0, IF(I37=H37,0,$D100), G100+H91-H82) -> 1943.925 | I100: =IF(I37=0, IF(J37=I37,0,$D100), H100+I91-I82) -> 2852.925 | J100: =IF(J37=0, IF(K37=J37,0,$D100), I100+J91-J82) -> 3004.425 | K100: =IF(K37=0, IF(L37=K37,0,$D100), J100+K91-K82) -> 3155.925 | L100: =IF(L37=0, IF(M37=L37,0,$D100), K100+L91-L82) -> 3307.425 | M100: =IF(M37=0, IF(N37=M37,0,$D100), L100+M91-M82) -> 2693.85 | N100: =IF(N37=0, IF(O37=N37,0,$D100), M100+N91-N82) -> 2072.7 | O100: =IF(O37=0, IF(P37=O37,0,$D100), N100+O91-O82) -> 5269.35 | ... BO100: =IF(BO37=0, IF(BP37=BO37,0,$D100), BN100+BO91-BO82) -> 10358.641
C101: Joseph Retail Group | D101: 2700 | E101: =Assumptions!G24 -> Initial Balance (Pallets) | F101: [pallet] | G101: 2700 | H101: =IF(H38=0, IF(I38=H38,0,$D101), G101+H92-H83) -> 3327.2727 | I101: =IF(I38=0, IF(J38=I38,0,$D101), H101+I92-I83) -> 3954.5455 | J101: =IF(J38=0, IF(K38=J38,0,$D101), I101+J92-J83) -> 5209.0909 | K101: =IF(K38=0, IF(L38=K38,0,$D101), J101+K92-K83) -> 7090.9091 | L101: =IF(L38=0, IF(M38=L38,0,$D101), K101+L92-L83) -> 8345.4545 | M101: =IF(M38=0, IF(N38=M38,0,$D101), L101+M92-M83) -> 4581.8182 | N101: =IF(N38=0, IF(O38=N38,0,$D101), M101+N92-N83) -> 3954.5455 | O101: =IF(O38=0, IF(P38=O38,0,$D101), N101+O92-O83) -> 5836.3636 | ... BO101: =IF(BO38=0, IF(BP38=BO38,0,$D101), BN101+BO92-BO83) -> 47.077642
C102: Dim Collective | D102: 900 | E102: =Assumptions!G24 -> Initial Balance (Pallets) | F102: [pallet] | G102: 900 | H102: =IF(H39=0, IF(I39=H39,0,$D102), G102+H93-H84) -> 1641 | I102: =IF(I39=0, IF(J39=I39,0,$D102), H102+I93-I84) -> 2408 | J102: =IF(J39=0, IF(K39=J39,0,$D102), I102+J93-J84) -> 3552 | K102: =IF(K39=0, IF(L39=K39,0,$D102), J102+K93-K84) -> 5099 | L102: =IF(L39=0, IF(M39=L39,0,$D102), K102+L93-L84) -> 6373 | M102: =IF(M39=0, IF(N39=M39,0,$D102), L102+M93-M84) -> 4891 | N102: =IF(N39=0, IF(O39=N39,0,$D102), M102+N93-N84) -> 5008 | O102: =IF(O39=0, IF(P39=O39,0,$D102), N102+O93-O84) -> 6503 | ... BO102: =IF(BO39=0, IF(BP39=BO39,0,$D102), BN102+BO93-BO84) -> 41649.642
C103: Tim Forward Brands | D103: 1500 | E103: =Assumptions!G24 -> Initial Balance (Pallets) | F103: [pallet] | G103: 1500 | H103: =IF(H40=0, IF(I40=H40,0,$D103), G103+H94-H85) -> 0 | I103: =IF(I40=0, IF(J40=I40,0,$D103), H103+I94-I85) -> 0 | J103: =IF(J40=0, IF(K40=J40,0,$D103), I103+J94-J85) -> 0 | K103: =IF(K40=0, IF(L40=K40,0,$D103), J103+K94-K85) -> 0 | L103: =IF(L40=0, IF(M40=L40,0,$D103), K103+L94-L85) -> 0 | M103: =IF(M40=0, IF(N40=M40,0,$D103), L103+M94-M85) -> 0 | N103: =IF(N40=0, IF(O40=N40,0,$D103), M103+N94-N85) -> 0 | O103: =IF(O40=0, IF(P40=O40,0,$D103), N103+O94-O85) -> 0 | ... BO103: =IF(BO40=0, IF(BP40=BO40,0,$D103), BN103+BO94-BO85) -> 0
C104: Total Stored Pallets | F104: [pallet] | G104: =SUM(_xlfn.ANCHORARRAY(G98)) -> 11400 | H104: =SUM(H98:H103) -> 12036.981 | I104: =SUM(I98:I103) -> 17568.875 | J104: =SUM(J98:J103) -> 24579.399 | K104: =SUM(K98:K103) -> 32104.692 | L104: =SUM(L98:L103) -> 39412.405 | M104: =SUM(M98:M103) -> 27333.168 | N104: =SUM(N98:N103) -> 29922.8 | O104: =SUM(O98:O103) -> 44087.168 | ... BP104: =SUM(BP98:BP103) -> 0
B106: 4 Revenues
B108: Inbound Handling
B109: Inbound Handling Rate
C110: Inbound Handeling Rate | D110: =Assumptions!D16 -> 4.5 | E110: $/pallet | F110: [$] | H110: {=+D110*_xlfn.ANCHORARRAY(H31)} -> 4.5 | I110: 4.5 | J110: 4.5 | K110: 4.5 | L110: 4.5 | M110: 4.5 | N110: 4.5 | O110: 4.5 | P110: 4.5 | Q110: 4.5 | R110: 4.5 | S110: 4.5 | T110: 4.635 | U110: 4.635 | V110: 4.635 | W110: 4.635 | X110: 4.635 | Y110: 4.635 | Z110: 4.635 | AA110: 4.635 | AB110: 4.635 | AC110: 4.635 | AD110: 4.635 | AE110: 4.635 | AF110: 4.77405 | AG110: 4.77405 | AH110: 4.77405 | AI110: 4.77405 | AJ110: 4.77405 | AK110: 4.77405 | AL110: 4.77405 | AM110: 4.77405 | AN110: 4.77405 | AO110: 4.77405 | AP110: 4.77405 | AQ110: 4.77405 | AR110: 4.9172715 | AS110: 4.9172715 | AT110: 4.9172715 | AU110: 4.9172715 | AV110: 4.9172715 | AW110: 4.9172715 | AX110: 4.9172715 | AY110: 4.9172715 | AZ110: 4.9172715 | BA110: 4.9172715 | BB110: 4.9172715 | BC110: 4.9172715 | BD110: 5.0647896 | BE110: 5.0647896 | BF110: 5.0647896 | BG110: 5.0647896 | BH110: 5.0647896 | BI110: 5.0647896 | BJ110: 5.0647896 | BK110: 5.0647896 | BL110: 5.0647896 | BM110: 5.0647896 | BN110: 5.0647896 | BO110: 5.0647896
B112: Volume in inbound Pallets
C113: {=cust} -> Michael’s Market Goods | F113: {=_xlfn.XLOOKUP(C113,_xlfn.ANCHORARRAY($C$89),$F$89:$BP$94)} -> [pallet] | G113: 0 | H113: 18368.333 | I113: 19516.354 | J113: 21812.396 | K113: 25256.458 | L113: 27552.5 | M113: 20664.375 | N113: 19516.354 | O113: 22960.417 | P113: 24108.438 | Q113: 27552.5 | R113: 30996.562 | S113: 18081.328 | T113: 19286.75 | U113: 20492.172 | V113: 22903.016 | W113: 26519.281 | X113: 28930.125 | Y113: 21697.594 | Z113: 20492.172 | AA113: 24108.438 | AB113: 25313.859 | AC113: 28930.125 | AD113: 32546.391 | AE113: 18985.395 | AF113: 20251.088 | AG113: 21516.78 | AH113: 24048.166 | AI113: 27845.245 | AJ113: 30376.631 | AK113: 22782.473 | AL113: 21516.78 | AM113: 25313.859 | AN113: 26579.552 | AO113: 30376.631 | AP113: 34173.71 | AQ113: 19554.956 | AR113: 20858.62 | AS113: 22162.284 | AT113: 24769.611 | AU113: 28680.603 | AV113: 31287.93 | AW113: 23465.948 | AX113: 22162.284 | AY113: 26073.275 | AZ113: 27376.939 | BA113: 31287.93 | BB113: 35198.921 | BC113: 19946.055 | BD113: 21275.793 | BE113: 22605.53 | BF113: 25265.004 | BG113: 29254.215 | BH113: 31913.689 | BI113: 23935.267 | BJ113: 22605.53 | BK113: 26594.741 | BL113: 27924.478 | BM113: 31913.689 | BN113: 35902.9 | BO113: 20344.977 | BP113: 0
C114: Andrew Digital Commerce | F114: {=_xlfn.XLOOKUP(C114,_xlfn.ANCHORARRAY($C$89),$F$89:$BP$94)} -> [pallet] | G114: 0 | H114: 11575.2 | I114: 12465.6 | J114: 13356 | K114: 12465.6 | L114: 13356 | M114: 12465.6 | N114: 16027.2 | O114: 18698.4 | P114: 19588.8 | Q114: 31164 | R114: 39177.6 | S114: 14157.36 | T114: 12269.712 | U114: 13213.536 | V114: 14157.36 | W114: 13213.536 | X114: 14157.36 | Y114: 13213.536 | Z114: 16988.832 | AA114: 19820.304 | AB114: 20764.128 | AC114: 33033.84 | AD114: 41528.256 | AE114: 14440.507 | AF114: 12515.106 | AG114: 13477.807 | AH114: 14440.507 | AI114: 13477.807 | AJ114: 14440.507 | AK114: 13477.807 | AL114: 17328.609 | AM114: 20216.71 | AN114: 21179.411 | AO114: 33694.517 | AP114: 42358.821 | AQ114: 14440.507 | AR114: 12515.106 | AS114: 13477.807 | AT114: 14440.507 | AU114: 13477.807 | AV114: 14440.507 | AW114: 13477.807 | AX114: 17328.609 | AY114: 20216.71 | AZ114: 21179.411 | BA114: 33694.517 | BB114: 42358.821 | BC114: 14440.507 | BD114: 12515.106 | BE114: 13477.807 | BF114: 14440.507 | BG114: 13477.807 | BH114: 14440.507 | BI114: 13477.807 | BJ114: 17328.609 | BK114: 20216.71 | BL114: 21179.411 | BM114: 33694.517 | BN114: 42358.821 | BO114: 14440.507 | BP114: 0
C115: Anup Industrial Systems | F115: {=_xlfn.XLOOKUP(C115,_xlfn.ANCHORARRAY($C$89),$F$89:$BP$94)} -> [pallet] | G115: 0 | H115: 14536.425 | I115: 15301.5 | J115: 15301.5 | K115: 15301.5 | L115: 15301.5 | M115: 14536.425 | N115: 13771.35 | O115: 16831.65 | P115: 16831.65 | Q115: 16066.575 | R115: 15301.5 | S115: 14609.107 | T115: 14609.107 | U115: 15378.007 | V115: 15378.007 | W115: 15378.007 | X115: 15378.007 | Y115: 14609.107 | Z115: 13840.207 | AA115: 16915.808 | AB115: 16915.808 | AC115: 16146.908 | AD115: 15378.007 | AE115: 14609.107 | AF115: 14609.107 | AG115: 15378.007 | AH115: 15378.007 | AI115: 15378.007 | AJ115: 15378.007 | AK115: 14609.107 | AL115: 13840.207 | AM115: 16915.808 | AN115: 16915.808 | AO115: 16146.908 | AP115: 15378.007 | AQ115: 14463.016 | AR115: 14463.016 | AS115: 15224.227 | AT115: 15224.227 | AU115: 15224.227 | AV115: 15224.227 | AW115: 14463.016 | AX115: 13701.805 | AY115: 16746.65 | AZ115: 16746.65 | BA115: 15985.439 | BB115: 15224.227 | BC115: 14246.071 | BD115: 14246.071 | BE115: 14995.864 | BF115: 14995.864 | BG115: 14995.864 | BH115: 14995.864 | BI115: 14246.071 | BJ115: 13496.278 | BK115: 16495.45 | BL115: 16495.45 | BM115: 15745.657 | BN115: 14995.864 | BO115: 14032.38 | BP115: 0
C116: Joseph Retail Group | F116: {=_xlfn.XLOOKUP(C116,_xlfn.ANCHORARRAY($C$89),$F$89:$BP$94)} -> [pallet] | G116: 0 | H116: 10036.364 | I116: 10663.636 | J116: 11918.182 | K116: 13800 | L116: 15054.545 | M116: 11290.909 | N116: 10663.636 | O116: 12545.455 | P116: 13172.727 | Q116: 15054.545 | R116: 16936.364 | S116: 9032.7273 | T116: 9634.9091 | U116: 10237.091 | V116: 11441.455 | W116: 13248 | X116: 14452.364 | Y116: 10839.273 | Z116: 10237.091 | AA116: 12043.636 | AB116: 12645.818 | AC116: 14452.364 | AD116: 16258.909 | AE116: 8490.7636 | AF116: 9056.8145 | AG116: 9622.8655 | AH116: 10754.967 | AI116: 12453.12 | AJ116: 13585.222 | AK116: 10188.916 | AL116: 9622.8655 | AM116: 11321.018 | AN116: 11887.069 | AO116: 13585.222 | AP116: 15283.375 | AQ116: 7811.5025 | AR116: 8332.2694 | AS116: 8853.0362 | AT116: 9894.5699 | AU116: 11456.87 | AV116: 12498.404 | AW116: 9373.8031 | AX116: 8853.0362 | AY116: 10415.337 | AZ116: 10936.104 | BA116: 12498.404 | BB116: 14060.705 | BC116: 7264.6974 | BD116: 7749.0105 | BE116: 8233.3237 | BF116: 9201.95 | BG116: 10654.889 | BH116: 11623.516 | BI116: 8717.6368 | BJ116: 8233.3237 | BK116: 9686.2632 | BL116: 10170.576 | BM116: 11623.516 | BN116: 13076.455 | BO116: 6756.1686 | BP116: 0
C117: Dim Collective | F117: {=_xlfn.XLOOKUP(C117,_xlfn.ANCHORARRAY($C$89),$F$89:$BP$94)} -> [pallet] | G117: 0 | H117: 5616 | I117: 5967 | J117: 6669 | K117: 7722 | L117: 8424 | M117: 6318 | N117: 5967 | O117: 7020 | P117: 7371 | Q117: 8424 | R117: 9477 | S117: 6054.75 | T117: 6458.4 | U117: 6862.05 | V117: 7669.35 | W117: 8880.3 | X117: 9687.6 | Y117: 7265.7 | Z117: 6862.05 | AA117: 8073 | AB117: 8476.65 | AC117: 9687.6 | AD117: 10898.55 | AE117: 6660.225 | AF117: 7104.24 | AG117: 7548.255 | AH117: 8436.285 | AI117: 9768.33 | AJ117: 10656.36 | AK117: 7992.27 | AL117: 7548.255 | AM117: 8880.3 | AN117: 9324.315 | AO117: 10656.36 | AP117: 11988.405 | AQ117: 7059.8385 | AR117: 7530.4944 | AS117: 8001.1503 | AT117: 8942.4621 | AU117: 10354.43 | AV117: 11295.742 | AW117: 8471.8062 | AX117: 8001.1503 | AY117: 9413.118 | AZ117: 9883.7739 | BA117: 11295.742 | BB117: 12707.709 | BC117: 7342.232 | BD117: 7831.7142 | BE117: 8321.1963 | BF117: 9300.1606 | BG117: 10768.607 | BH117: 11747.571 | BI117: 8810.6784 | BJ117: 8321.1963 | BK117: 9789.6427 | BL117: 10279.125 | BM117: 11747.571 | BN117: 13216.018 | BO117: 7635.9213 | BP117: 0
C118: Tim Forward Brands | F118: {=_xlfn.XLOOKUP(C118,_xlfn.ANCHORARRAY($C$89),$F$89:$BP$94)} -> [pallet] | G118: 0 | H118: 0 | I118: 0 | J118: 0 | K118: 0 | L118: 0 | M118: 0 | N118: 0 | O118: 0 | P118: 0 | Q118: 0 | R118: 0 | S118: 0 | T118: 0 | U118: 0 | V118: 0 | W118: 0 | X118: 0 | Y118: 0 | Z118: 0 | AA118: 0 | AB118: 0 | AC118: 0 | AD118: 0 | AE118: 0 | AF118: 0 | AG118: 0 | AH118: 0 | AI118: 0 | AJ118: 0 | AK118: 0 | AL118: 0 | AM118: 0 | AN118: 0 | AO118: 0 | AP118: 0 | AQ118: 0 | AR118: 0 | AS118: 0 | AT118: 0 | AU118: 0 | AV118: 0 | AW118: 0 | AX118: 0 | AY118: 0 | AZ118: 0 | BA118: 0 | BB118: 0 | BC118: 0 | BD118: 0 | BE118: 0 | BF118: 0 | BG118: 0 | BH118: 0 | BI118: 0 | BJ118: 0 | BK118: 0 | BL118: 0 | BM118: 0 | BN118: 0 | BO118: 0 | BP118: 0
B120: Revenue from Inbound Handling
C121: {=cust} -> Michael’s Market Goods | F121: [$] | H121: {=_xlfn.ANCHORARRAY(H110)*H113:BO118*H35:BO40} -> 82657.5 | I121: 87823.594 | J121: 98155.781 | K121: 113654.06 | L121: 123986.25 | M121: 92989.688 | N121: 87823.594 | O121: 103321.88 | P121: 108487.97 | Q121: 123986.25 | R121: 139484.53 | S121: 81365.977 | T121: 89394.086 | U121: 94981.217 | V121: 106155.48 | W121: 122916.87 | X121: 134091.13 | Y121: 100568.35 | Z121: 94981.217 | AA121: 111742.61 | AB121: 117329.74 | AC121: 134091.13 | AD121: 150852.52 | AE121: 87997.304 | AF121: 96679.704 | AG121: 102722.19 | AH121: 114807.15 | AI121: 132934.59 | AJ121: 145019.56 | AK121: 108764.67 | AL121: 102722.19 | AM121: 120849.63 | AN121: 126892.11 | AO121: 145019.56 | AP121: 163147 | AQ121: 93356.339 | AR121: 102567.5 | AS121: 108977.97 | AT121: 121798.9 | AU121: 141030.31 | AV121: 153851.25 | AW121: 115388.44 | AX121: 108977.97 | AY121: 128209.37 | AZ121: 134619.84 | BA121: 153851.25 | BB121: 173082.65 | BC121: 98080.17 | BD121: 107757.41 | BE121: 114492.25 | BF121: 127961.93 | BG121: 148166.44 | BH121: 161636.12 | BI121: 121227.09 | BJ121: 114492.25 | BK121: 134696.77 | BL121: 141431.61 | BM121: 161636.12 | BN121: 181840.64 | BO121: 103043.03
C122: Andrew Digital Commerce | F122: [$] | H122: 52088.4 | I122: 56095.2 | J122: 60102 | K122: 56095.2 | L122: 60102 | M122: 56095.2 | N122: 72122.4 | O122: 84142.8 | P122: 88149.6 | Q122: 140238 | R122: 176299.2 | S122: 63708.12 | T122: 56870.115 | U122: 61244.739 | V122: 65619.364 | W122: 61244.739 | X122: 65619.364 | Y122: 61244.739 | Z122: 78743.236 | AA122: 91867.109 | AB122: 96241.733 | AC122: 153111.85 | AD122: 192483.47 | AE122: 66931.751 | AF122: 59747.743 | AG122: 64343.723 | AH122: 68939.703 | AI122: 64343.723 | AJ122: 68939.703 | AK122: 64343.723 | AL122: 82727.644 | AM122: 96515.585 | AN122: 101111.56 | AO122: 160859.31 | AP122: 202223.13 | AQ122: 68939.703 | AR122: 61540.175 | AS122: 66274.035 | AT122: 71007.895 | AU122: 66274.035 | AV122: 71007.895 | AW122: 66274.035 | AX122: 85209.473 | AY122: 99411.052 | AZ122: 104144.91 | BA122: 165685.09 | BB122: 208289.82 | BC122: 71007.895 | BD122: 63386.38 | BE122: 68262.256 | BF122: 73138.131 | BG122: 68262.256 | BH122: 73138.131 | BI122: 68262.256 | BJ122: 87765.758 | BK122: 102393.38 | BL122: 107269.26 | BM122: 170655.64 | BN122: 214538.52 | BO122: 73138.131
C123: Anup Industrial Systems | F123: [$] | H123: 65413.912 | I123: 68856.75 | J123: 68856.75 | K123: 68856.75 | L123: 68856.75 | M123: 65413.912 | N123: 61971.075 | O123: 75742.425 | P123: 75742.425 | Q123: 72299.588 | R123: 68856.75 | S123: 65740.982 | T123: 67713.212 | U123: 71277.065 | V123: 71277.065 | W123: 71277.065 | X123: 71277.065 | Y123: 67713.212 | Z123: 64149.358 | AA123: 78404.771 | AB123: 78404.771 | AC123: 74840.918 | AD123: 71277.065 | AE123: 67713.212 | AF123: 69744.608 | AG123: 73415.377 | AH123: 73415.377 | AI123: 73415.377 | AJ123: 73415.377 | AK123: 69744.608 | AL123: 66073.839 | AM123: 80756.914 | AN123: 80756.914 | AO123: 77086.146 | AP123: 73415.377 | AQ123: 69047.162 | AR123: 71118.577 | AS123: 74861.66 | AT123: 74861.66 | AU123: 74861.66 | AV123: 74861.66 | AW123: 71118.577 | AX123: 67375.494 | AY123: 82347.826 | AZ123: 82347.826 | BA123: 78604.743 | BB123: 74861.66 | BC123: 70051.798 | BD123: 72153.352 | BE123: 75950.897 | BF123: 75950.897 | BG123: 75950.897 | BH123: 75950.897 | BI123: 72153.352 | BJ123: 68355.807 | BK123: 83545.986 | BL123: 83545.986 | BM123: 79748.442 | BN123: 75950.897 | BO123: 71071.052
C124: Joseph Retail Group | F124: [$] | H124: 45163.636 | I124: 47986.364 | J124: 53631.818 | K124: 62100 | L124: 67745.455 | M124: 50809.091 | N124: 47986.364 | O124: 56454.545 | P124: 59277.273 | Q124: 67745.455 | R124: 76213.636 | S124: 40647.273 | T124: 44657.804 | U124: 47448.916 | V124: 53031.142 | W124: 61404.48 | X124: 66986.705 | Y124: 50240.029 | Z124: 47448.916 | AA124: 55822.255 | AB124: 58613.367 | AC124: 66986.705 | AD124: 75360.044 | AE124: 39354.689 | AF124: 43237.685 | AG124: 45940.041 | AH124: 51344.752 | AI124: 59451.818 | AJ124: 64856.528 | AK124: 48642.396 | AL124: 45940.041 | AM124: 54047.107 | AN124: 56749.462 | AO124: 64856.528 | AP124: 72963.594 | AQ124: 37292.504 | AR124: 40972.031 | AS124: 43532.783 | AT124: 48654.287 | AU124: 56336.542 | AV124: 61458.046 | AW124: 46093.535 | AX124: 43532.783 | AY124: 51215.038 | AZ124: 53775.79 | BA124: 61458.046 | BB124: 69140.302 | BC124: 35722.489 | BD124: 39247.108 | BE124: 41700.053 | BF124: 46605.941 | BG124: 53964.774 | BH124: 58870.662 | BI124: 44152.997 | BJ124: 41700.053 | BK124: 49058.885 | BL124: 51511.83 | BM124: 58870.662 | BN124: 66229.495 | BO124: 34218.573
C125: Dim Collective | F125: [$] | H125: 25272 | I125: 26851.5 | J125: 30010.5 | K125: 34749 | L125: 37908 | M125: 28431 | N125: 26851.5 | O125: 31590 | P125: 33169.5 | Q125: 37908 | R125: 42646.5 | S125: 27246.375 | T125: 29934.684 | U125: 31805.602 | V125: 35547.437 | W125: 41160.191 | X125: 44902.026 | Y125: 33676.52 | Z125: 31805.602 | AA125: 37418.355 | AB125: 39289.273 | AC125: 44902.026 | AD125: 50514.779 | AE125: 30870.143 | AF125: 33915.997 | AG125: 36035.747 | AH125: 40275.246 | AI125: 46634.496 | AJ125: 50873.995 | AK125: 38155.497 | AL125: 36035.747 | AM125: 42394.996 | AN125: 44514.746 | AO125: 50873.995 | AP125: 57233.245 | AQ125: 33704.022 | AR125: 37029.485 | AS125: 39343.828 | AT125: 43972.514 | AU125: 50915.543 | AV125: 55544.228 | AW125: 41658.171 | AX125: 39343.828 | AY125: 46286.857 | AZ125: 48601.2 | BA125: 55544.228 | BB125: 62487.257 | BC125: 36103.748 | BD125: 39665.985 | BE125: 42145.109 | BF125: 47103.357 | BG125: 54540.729 | BH125: 59498.977 | BI125: 44624.233 | BJ125: 42145.109 | BK125: 49582.481 | BL125: 52061.605 | BM125: 59498.977 | BN125: 66936.349 | BO125: 38674.335
C126: Tim Forward Brands | F126: [$] | H126: 0 | I126: 0 | J126: 0 | K126: 0 | L126: 0 | M126: 0 | N126: 0 | O126: 0 | P126: 0 | Q126: 0 | R126: 0 | S126: 0 | T126: 0 | U126: 0 | V126: 0 | W126: 0 | X126: 0 | Y126: 0 | Z126: 0 | AA126: 0 | AB126: 0 | AC126: 0 | AD126: 0 | AE126: 0 | AF126: 0 | AG126: 0 | AH126: 0 | AI126: 0 | AJ126: 0 | AK126: 0 | AL126: 0 | AM126: 0 | AN126: 0 | AO126: 0 | AP126: 0 | AQ126: 0 | AR126: 0 | AS126: 0 | AT126: 0 | AU126: 0 | AV126: 0 | AW126: 0 | AX126: 0 | AY126: 0 | AZ126: 0 | BA126: 0 | BB126: 0 | BC126: 0 | BD126: 0 | BE126: 0 | BF126: 0 | BG126: 0 | BH126: 0 | BI126: 0 | BJ126: 0 | BK126: 0 | BL126: 0 | BM126: 0 | BN126: 0 | BO126: 0
C127: Total Revenue - Inbound Handleing | F127: [$] | H127: =SUM(H121:H126) -> 270595.45 | I127: =SUM(I121:I126) -> 287613.41 | J127: =SUM(J121:J126) -> 310756.85 | K127: =SUM(K121:K126) -> 335455.01 | L127: =SUM(L121:L126) -> 358598.45 | M127: =SUM(M121:M126) -> 293738.89 | N127: =SUM(N121:N126) -> 296754.93 | O127: =SUM(O121:O126) -> 351251.65 | ... BP127: =SUM(BP121:BP126) -> 0
B129: Outbound Picking
B130: Outbound Picking
C131: Outbound Pricing rate | D131: =Assumptions!D17 -> 0.35 | E131: $/pallet | F131: [$] | H131: {=$D$131*_xlfn.ANCHORARRAY(H31)} -> 0.35 | I131: 0.35 | J131: 0.35 | K131: 0.35 | L131: 0.35 | M131: 0.35 | N131: 0.35 | O131: 0.35 | P131: 0.35 | Q131: 0.35 | R131: 0.35 | S131: 0.35 | T131: 0.3605 | U131: 0.3605 | V131: 0.3605 | W131: 0.3605 | X131: 0.3605 | Y131: 0.3605 | Z131: 0.3605 | AA131: 0.3605 | AB131: 0.3605 | AC131: 0.3605 | AD131: 0.3605 | AE131: 0.3605 | AF131: 0.371315 | AG131: 0.371315 | AH131: 0.371315 | AI131: 0.371315 | AJ131: 0.371315 | AK131: 0.371315 | AL131: 0.371315 | AM131: 0.371315 | AN131: 0.371315 | AO131: 0.371315 | AP131: 0.371315 | AQ131: 0.371315 | AR131: 0.38245445 | AS131: 0.38245445 | AT131: 0.38245445 | AU131: 0.38245445 | AV131: 0.38245445 | AW131: 0.38245445 | AX131: 0.38245445 | AY131: 0.38245445 | AZ131: 0.38245445 | BA131: 0.38245445 | BB131: 0.38245445 | BC131: 0.38245445 | BD131: 0.39392808 | BE131: 0.39392808 | BF131: 0.39392808 | BG131: 0.39392808 | BH131: 0.39392808 | BI131: 0.39392808 | BJ131: 0.39392808 | BK131: 0.39392808 | BL131: 0.39392808 | BM131: 0.39392808 | BN131: 0.39392808 | BO131: 0.39392808
B133: Volume in Parcels
...

Sheet Model Validation
C2: Questions & Answers
B4: # | C4: Question | D4: Points | E4: Section | F4: Answer | G4: Correct Answer
B6: Part 1 - Without the New Client
B7: 1 | C7: What are the Anup Industrial Systems Outbound Parcels in 03/2026? | D7: 20 | E7: =--(F7=G7) -> 1 | F7: =Model!J65 -> 227250 | G7: 227250
B8: 2 | C8: What are the Michael’s Market Goods Outbound Pallets in year 2027? | D8: 20 | E8: =--(F8=G8) -> 1 | F8: =SUM(Model!T80:AE80) -> 280875 | G8: 280875
B9: 3 | C9: What are the Andrew Digital Commerce Inbound Pallets in 11/2027? | D9: 25 | E9: =--(F9=G9) -> 1 | F9: =ROUND(Model!AD90,0) -> 41528 | G9: 41528
B10: 4 | C10: What is the monthly peak total revenue from pallets storage of 2026? | D10: 25 | E10: =--(F10=G10) -> 0 | G10: 517244
B11: 5 | C11: What is the total revenue from inbound handling over the 5-year period? | D11: 25 | E11: =--(F11=G11) -> 1 | F11: =ROUND(SUM(Model!H127:BO127),0) -> 22681102 | G11: 22681102
B12: 6 | C12: How many FTE will be needed to handle the Replenishment in 01/2026? | D12: 25 | E12: =--(F12=G12) -> 1 | F12: =ROUND(Model!H222,2) -> 24.16 | G12: 24.16
B13: 7 | C13: How many temporary staff will be needed in 11/2026? | D13: 25 | E13: =--(F13=G13) -> 1 | F13: =ROUND(Model!R234,0) -> 110 | G13: 110
B14: 8 | C14: Assuming you had 1 more permanent staff in 2026, how much money would you save during the year by not using a temporary worker? | D14: 25 | E14: =--(F14=G14) -> 1 | F14: =ROUND(SUM(Model!H250:S250),0) -> 1280 | G14: 1280
B15: 9 | C15: How many additional permanent staff will be hired at the beginning of 2027? | D15: 25 | E15: =--(F15=G15) -> 1 | F15: =Model!T229 -> 2 | G15: 2
B16: 10 | C16: What is the total cost of temporary staff over the 5-year period? | D16: 25 | E16: =--(F16=G16) -> 1 | F16: =ROUND(SUM(Model!H244:BO244),0) -> 11150061 | G16: 11150061
B17: 11 | C17: How many Reach Trucks will be needed to handle the Replenishment in 01/2026? | D17: 20 | E17: =--(F17=G17) -> 1 | F17: 8.05 | G17: 8.05
B18: 12 | C18: How many Power Pallet Trucks will be needed for all activities in 02/2026? | D18: 20 | E18: =--(F18=G18) -> 1 | F18: =Model!I309 -> 34 | G18: 34
B19: 13 | C19: Which month will you buy the first additional Reach Truck? | D19: 25 | E19: =--(F19=G19) -> 1 | F19: 46143 | G19: 46143
B20: 14 | C20: What is the total amount invested into the trucks over the 5-year period? | D20: 25 | E20: =--(F20=G20) -> 1 | F20: =ROUND(SUM(_xlfn.ANCHORARRAY(Model!H326)),0) -> 1254790 | G20: 1254790
B21: 15 | C21: How many hours Powered Pallet Trucks will be used in 03/2026 for Inbound Unloading Activity? | D21: 25 | E21: =--(F21=G21) -> 1 | F21: =ROUND(Model!J285,0) -> 4834 | G21: 4834
B22: 16 | C22: What is the total cost of energy consumption by all trucks for 01/2027? | D22: 25 | E22: =--(F22=G22) -> 1 | F22: =ROUND(Model!T341,0) -> 19003 | G22: 19003
B23: 17 | C23: What is the amount of fixed COGS incurred in 01/2027? | D23: 20 | E23: =--(F23=G23) -> 1 | F23: =Model!T350 -> 61800 | G23: 61800
B24: 18 | C24: What is the total amount of SG&A costs incurred over the 5-year period? | D24: 20 | E24: =--(F24=G24) -> 1 | F24: =-ROUND(SUM(_xlfn.ANCHORARRAY(Model!H24)),0) -> 3981852 | G24: 3981852
B25: 19 | C25: What is the total EBITDA for the 5-year period? | D25: 50 | E25: =--(F25=G25) -> 0 | F25: =ROUND(Model!E17,0) -> 0 | G25: 55621678
B27: Part 2 - With the New Client
B28: 20 | C28: If Tim Forward Brands sign the contract, what is the total EBITDA for the 5-year period? | D28: 30 | E28: =--(F28=G28) -> 0 | F28: =ROUND(Model!E16,0) -> 0 | G28: 61161159
D30: 500

Sheet _avcts_version_hash
A1: i1OwNHgEFD7u0auo+Co71V9hKviRajTQWEUZo+yMHv8KRTVltoK89vUtgaZa9WvkoPPvK5pehJezplZYqVf4UNSJFDbCFFOUkz2Iv3abUXo6IhuNv1jmsp7DvEhQbpVogQKJGURxAFAwXfKVo53wJFASqhGt8cuKwG4jZZ69d+FjgTe78eBYzTIUgU9a4da1xilS
